[
    {
        "name": "New Anglian Confederation (NAC) Royal Space Navy",
        "ships": [
            {"hull":{"points":2,"rows":4,"stealth":"0","streamlining":"none"},"armour":[],"systems":[{"name":"drive","thrust":4,"advanced":false,"id":"MmlSY"},{"name":"ftl","advanced":false,"id":"EGhZS"},{"name":"fireControl","id":"dqDWq"}],"weapons":[{"name":"beam","class":1,"leftArc":"F","numArcs":6,"id":"P361Y"}],"ordnance":[],"extras":[],"fighters":[],"orientation":"alpha","points":21,"cpv":16,"mass":6,"class":"Scoutship","name":"Harrison"},
            {"hull":{"points":2,"rows":4,"stealth":"0","streamlining":"none"},"armour":[[1,0]],"systems":[{"name":"drive","thrust":6,"advanced":false,"id":"1zfvj"},{"name":"ftl","advanced":false,"id":"RshDj"},{"name":"fireControl","id":"ZHfb7"}],"weapons":[{"name":"pds","id":"uJDZW"},{"name":"beam","class":1,"leftArc":"F","numArcs":6,"id":"n3wwP"},{"name":"beam","class":1,"leftArc":"F","numArcs":6,"id":"S_Kzy"}],"ordnance":[],"extras":[],"fighters":[],"orientation":"alpha","points":41,"cpv":30,"mass":12,"class":"Corvette","name":"Arapaho"},
            {"hull":{"points":5,"rows":4,"stealth":"0","streamlining":"none"},"armour":[],"systems":[{"name":"drive","thrust":6,"advanced":false,"id":"zf9y8"},{"name":"ftl","advanced":false,"id":"Qr9PQ"},{"name":"fireControl","id":"JTGf2"}],"weapons":[{"name":"pds","id":"Hs4O-"},{"name":"beam","class":1,"leftArc":"F","numArcs":6,"id":"3kh2s"},{"name":"beam","class":1,"leftArc":"F","numArcs":6,"id":"f56Dd"},{"name":"beam","class":2,"leftArc":"FP","numArcs":3,"id":"zv_xM"}],"ordnance":[],"extras":[],"fighters":[],"orientation":"alpha","points":61,"cpv":46,"mass":18,"class":"Frigate","name":"Minerva"},
            {"hull":{"points":7,"rows":4,"stealth":"0","streamlining":"none"},"armour":[],"systems":[{"name":"drive","thrust":6,"advanced":false,"id":"DwUcR"},{"name":"ftl","advanced":false,"id":"WVQVf"},{"name":"fireControl","id":"ZM92p"}],"weapons":[{"name":"pds","id":"VYLpj"},{"name":"beam","class":1,"leftArc":"F","numArcs":6,"id":"ah3tc"},{"name":"beam","class":1,"leftArc":"F","numArcs":6,"id":"V7qSa"},{"name":"beam","class":2,"leftArc":"F","numArcs":3,"id":"_xSaG"},{"name":"beam","class":2,"leftArc":"AP","numArcs":3,"id":"_mD0R"}],"ordnance":[],"extras":[],"fighters":[],"orientation":"alpha","points":81,"cpv":63,"mass":24,"class":"Heavy Frigate","name":"Tacoma"},
            {"hull":{"points":9,"rows":4,"stealth":"0","streamlining":"none"},"armour":[],"systems":[{"name":"drive","thrust":6,"advanced":false,"id":"R5kU_"},{"name":"ftl","advanced":false,"id":"Te_Uq"},{"name":"fireControl","id":"BzLZ9"}],"weapons":[{"name":"pds","id":"CPrQH"},{"name":"pds","id":"PAqSO"},{"name":"beam","class":1,"leftArc":"F","numArcs":6,"id":"M7Hs_"},{"name":"beam","class":1,"leftArc":"F","numArcs":6,"id":"h0SLE"},{"name":"beam","class":2,"leftArc":"AP","numArcs":3,"id":"Vs4cy"},{"name":"beam","class":2,"leftArc":"F","numArcs":3,"id":"lyZ7F"}],"ordnance":[],"extras":[],"fighters":[],"orientation":"alpha","points":100,"cpv":79,"mass":30,"class":"Destroyer","name":"Ticonderoga"},
            {"hull":{"points":15,"rows":4,"stealth":"0","streamlining":"none"},"armour":[],"systems":[{"name":"drive","thrust":6,"advanced":false,"id":"Aelkh"},{"name":"ftl","advanced":false,"id":"ARMh6"},{"name":"fireControl","id":"b6wSX"},{"name":"fireControl","id":"uqBd0"},{"name":"screen","area":false,"advanced":false,"id":"sxR_4"}],"weapons":[{"name":"pds","id":"mJ1LG"},{"name":"pds","id":"JVtOh"},{"name":"beam","class":1,"leftArc":"F","numArcs":6,"id":"iPyuR"},{"name":"beam","class":1,"leftArc":"F","numArcs":6,"id":"1kVoS"},{"name":"beam","class":2,"leftArc":"FP","numArcs":3,"id":"laFNH"},{"name":"beam","class":2,"leftArc":"AP","numArcs":3,"id":"XI5HA"},{"name":"beam","class":2,"leftArc":"F","numArcs":3,"id":"eMjUS"}],"ordnance":[],"extras":[],"fighters":[],"orientation":"alpha","points":167,"cpv":142,"mass":50,"class":"Light Cruiser","name":"Huron"},
            {"hull":{"points":19,"rows":4,"stealth":"0","streamlining":"none"},"armour":[[3,0]],"systems":[{"name":"drive","thrust":4,"advanced":false,"id":"m5PBF"},{"name":"ftl","advanced":false,"id":"3i5wC"},{"name":"fireControl","id":"zIST4"},{"name":"fireControl","id":"rRJ7q"},{"name":"adfc","id":"wHWH0"},{"name":"screen","area":false,"advanced":false,"id":"_kwVI"}],"weapons":[{"name":"torpedoPulse","leftArc":"F","numArcs":1,"id":"8PMyf"},{"name":"pds","id":"gW9DZ"},{"name":"pds","id":"lOWFz"},{"name":"pds","id":"k8huo"},{"name":"beam","class":1,"leftArc":"F","numArcs":6,"id":"mwnwS"},{"name":"beam","class":2,"leftArc":"F","numArcs":3,"id":"h3Het"},{"name":"beam","class":2,"leftArc":"AP","numArcs":3,"id":"aVH23"},{"name":"beam","class":3,"leftArc":"F","numArcs":1,"id":"fjC2F"}],"ordnance":[],"extras":[],"fighters":[],"orientation":"alpha","points":219,"cpv":196,"mass":64,"class":"Escort Cruiser","name":"Furious"},
            {"hull":{"points":24,"rows":4,"stealth":"0","streamlining":"none"},"armour":[[5,0]],"systems":[{"name":"drive","thrust":6,"advanced":false,"id":"m1bLU"},{"name":"ftl","advanced":false,"id":"FQ85U"},{"name":"fireControl","id":"0oUe8"},{"name":"fireControl","id":"Mvn94"},{"name":"screen","area":false,"advanced":false,"id":"_Zv3o"}],"weapons":[{"name":"pds","id":"mgNfc"},{"name":"pds","id":"dd3Gp"},{"name":"beam","class":1,"leftArc":"F","numArcs":6,"id":"Psc1z"},{"name":"beam","class":2,"leftArc":"F","numArcs":3,"id":"87WEJ"},{"name":"beam","class":2,"leftArc":"AP","numArcs":3,"id":"9kJOb"},{"name":"beam","class":3,"leftArc":"FP","numArcs":3,"id":"k3FUy"}],"ordnance":[],"extras":[],"fighters":[],"orientation":"alpha","points":261,"cpv":245,"mass":80,"class":"Heavy Cruiser","name":"Vandenburg"},
            {"hull":{"points":32,"rows":4,"stealth":"0","streamlining":"none"},"armour":[[5,0]],"systems":[{"name":"drive","thrust":4,"advanced":false,"id":"cEt8m"},{"name":"ftl","advanced":false,"id":"skMOm"},{"name":"fireControl","id":"BfQ1D"},{"name":"fireControl","id":"vX0wR"},{"name":"fireControl","id":"b2CpD"},{"name":"screen","area":false,"advanced":false,"id":"S2V3k"},{"name":"magazine","capacity":3,"id":"X7AaO"}],"weapons":[{"name":"pds","id":"Yw2J-"},{"name":"pds","id":"ygrA2"},{"name":"pds","id":"peMHO"},{"name":"beam","class":1,"leftArc":"F","numArcs":6,"id":"aT-md"},{"name":"beam","class":1,"leftArc":"F","numArcs":6,"id":"jr3Aq"},{"name":"beam","class":2,"leftArc":"F","numArcs":6,"id":"m1GpX"},{"name":"beam","class":3,"leftArc":"AP","numArcs":3,"id":"wwyXG"},{"name":"beam","class":3,"leftArc":"F","numArcs":3,"id":"LvNiM"}],"ordnance":[{"name":"salvoLauncher","leftArc":"FP","numArcs":3,"id":"p0j5K","magazine":"X7AaO"}],"extras":[],"fighters":[],"orientation":"alpha","points":358,"cpv":364,"mass":106,"class":"Battlecruiser","name":"Majestic"},
            {"hull":{"points":36,"rows":4,"stealth":"0","streamlining":"none"},"armour":[[5,0]],"systems":[{"name":"drive","thrust":4,"advanced":false,"id":"etkut"},{"name":"ftl","advanced":false,"id":"cv0WF"},{"name":"fireControl","id":"8vzMJ"},{"name":"fireControl","id":"oQwdG"},{"name":"fireControl","id":"EpKxp"},{"name":"screen","area":false,"advanced":false,"id":"DZMNn"}],"weapons":[{"name":"pds","id":"EQS56"},{"name":"pds","id":"3Gmc0"},{"name":"pds","id":"DBUW_"},{"name":"torpedoPulse","leftArc":"F","numArcs":1,"id":"yDTwC"},{"name":"torpedoPulse","leftArc":"F","numArcs":1,"id":"kZzf-"},{"name":"beam","class":1,"leftArc":"F","numArcs":6,"id":"RtmOk"},{"name":"beam","class":1,"leftArc":"F","numArcs":6,"id":"A5sv8"},{"name":"beam","class":2,"leftArc":"F","numArcs":6,"id":"Lq0yU"},{"name":"beam","class":3,"leftArc":"FP","numArcs":3,"id":"FDZLx"},{"name":"beam","class":3,"leftArc":"AP","numArcs":3,"id":"EGH7R"},{"name":"beam","class":3,"leftArc":"F","numArcs":3,"id":"ZOIvw"}],"ordnance":[],"extras":[],"fighters":[],"orientation":"alpha","points":406,"cpv":430,"mass":120,"class":"Battleship","name":"Victoria"},
            {"hull":{"points":42,"rows":4,"stealth":"0","streamlining":"none"},"armour":[[7,0]],"systems":[{"name":"drive","thrust":4,"advanced":false,"id":"eL6rL"},{"name":"ftl","advanced":false,"id":"028Nj"},{"name":"fireControl","id":"EISzu"},{"name":"fireControl","id":"J-lkC"},{"name":"fireControl","id":"EEI6Q"},{"name":"screen","area":false,"advanced":false,"id":"fMn4y"},{"name":"hangar","id":"ZXCAt","isRack":false,"critRules":false}],"weapons":[{"name":"pds","id":"rvufi"},{"name":"pds","id":"kZ-qO"},{"name":"pds","id":"brQsS"},{"name":"torpedoPulse","leftArc":"F","numArcs":1,"id":"iK4rR"},{"name":"beam","class":1,"leftArc":"F","numArcs":6,"id":"JWUDT"},{"name":"beam","class":1,"leftArc":"F","numArcs":6,"id":"jOEuw"},{"name":"beam","class":2,"leftArc":"F","numArcs":6,"id":"zM3tx"},{"name":"beam","class":3,"leftArc":"FP","numArcs":3,"id":"GtMR1"},{"name":"beam","class":3,"leftArc":"AP","numArcs":3,"id":"FwMyW"},{"name":"beam","class":3,"leftArc":"F","numArcs":3,"id":"CmhzJ"}],"ordnance":[],"extras":[],"fighters":[{"name":"fighters","type":"standard","id":"MYWuB","mods":[],"hangar":"ZXCAt"}],"orientation":"alpha","points":472,"cpv":486,"mass":140,"class":"Battledreadnought","name":"Excalibur"},
            {"hull":{"points":57,"rows":4,"stealth":"0","streamlining":"none"},"armour":[[7,0]],"systems":[{"name":"drive","thrust":4,"advanced":false,"id":"k5-fR"},{"name":"ftl","advanced":false,"id":"FBbFx"},{"name":"fireControl","id":"OUPYJ"},{"name":"fireControl","id":"l2K4o"},{"name":"fireControl","id":"niQ-g"},{"name":"screen","area":false,"advanced":false,"id":"cQVeu"},{"name":"hangar","id":"j4Em0","isRack":false,"critRules":false},{"name":"hangar","id":"PfKM_","isRack":false,"critRules":false}],"weapons":[{"name":"pds","id":"89Azz"},{"name":"pds","id":"BwDIk"},{"name":"pds","id":"_Fhc-"},{"name":"pds","id":"J35yb"},{"name":"torpedoPulse","leftArc":"F","numArcs":1,"id":"AJvty"},{"name":"torpedoPulse","leftArc":"F","numArcs":1,"id":"N563i"},{"name":"beam","class":1,"leftArc":"F","numArcs":6,"id":"aYS1I"},{"name":"beam","class":1,"leftArc":"F","numArcs":6,"id":"uyNlX"},{"name":"beam","class":2,"leftArc":"F","numArcs":6,"id":"NJ-s3"},{"name":"beam","class":2,"leftArc":"F","numArcs":6,"id":"EWOol"},{"name":"beam","class":3,"leftArc":"FP","numArcs":3,"id":"I28GT"},{"name":"beam","class":3,"leftArc":"AP","numArcs":3,"id":"dQ8U9"},{"name":"beam","class":3,"leftArc":"F","numArcs":3,"id":"wrSKK"}],"ordnance":[],"extras":[],"fighters":[{"name":"fighters","type":"standard","id":"5ADRS","mods":[],"hangar":"j4Em0"},{"name":"fighters","type":"standard","id":"RJXTg","mods":[],"hangar":"PfKM_"}],"orientation":"alpha","points":642,"cpv":712,"mass":190,"class":"Superdreadnought","name":"Valley Forge"},
            {"hull":{"points":28,"rows":4,"stealth":"0","streamlining":"none"},"armour":[[9,0]],"systems":[{"name":"drive","thrust":4,"advanced":false,"id":"9q-lH"},{"name":"ftl","advanced":false,"id":"llpza"},{"name":"fireControl","id":"lwHJf"},{"name":"fireControl","id":"Fa6jl"},{"name":"screen","area":false,"advanced":false,"id":"BeUun"},{"name":"screen","area":false,"advanced":false,"id":"Ck7Yk"},{"name":"hangar","id":"5vKqy","isRack":false,"critRules":false},{"name":"hangar","id":"PjteR","isRack":false,"critRules":false},{"name":"hangar","id":"5Dimf","isRack":false,"critRules":false},{"name":"hangar","id":"1guU_","isRack":false,"critRules":false}],"weapons":[{"name":"pds","id":"SR7EN"},{"name":"pds","id":"ssxp6"},{"name":"pds","id":"Vuic4"},{"name":"pds","id":"rurC1"},{"name":"beam","class":1,"leftArc":"F","numArcs":6,"id":"3MXwM"},{"name":"beam","class":1,"leftArc":"F","numArcs":6,"id":"ajzMP"},{"name":"beam","class":2,"leftArc":"F","numArcs":6,"id":"1-ayT"}],"ordnance":[],"extras":[],"fighters":[{"name":"fighters","type":"standard","id":"e4P1A","mods":[],"hangar":"5vKqy"},{"name":"fighters","type":"standard","id":"wjlfa","mods":[],"hangar":"PjteR"},{"name":"fighters","type":"standard","id":"9uBl2","mods":[],"hangar":"5Dimf"},{"name":"fighters","type":"standard","id":"MAEY_","mods":[],"hangar":"1guU_"}],"orientation":"alpha","points":483,"cpv":379,"mass":140,"class":"Light Fleet Carrier","name":"Inflexible"},
            {"hull":{"points":40,"rows":4,"stealth":"0","streamlining":"none"},"armour":[[12,0]],"systems":[{"name":"drive","thrust":4,"advanced":false,"id":"ZMeG4"},{"name":"ftl","advanced":false,"id":"xkeiI"},{"name":"screen","area":false,"advanced":false,"id":"6xtJ-"},{"name":"screen","area":false,"advanced":false,"id":"dliEP"},{"name":"fireControl","id":"yhsgC"},{"name":"fireControl","id":"1wgP5"},{"name":"hangar","id":"UuT4x","isRack":false,"critRules":false},{"name":"hangar","id":"FuQzk","isRack":false,"critRules":false},{"name":"hangar","id":"Dcz5t","isRack":false,"critRules":false},{"name":"hangar","id":"-DXfV","isRack":false,"critRules":false},{"name":"hangar","id":"sdszp","isRack":false,"critRules":false},{"name":"hangar","id":"atdd3","isRack":false,"critRules":false}],"weapons":[{"name":"pds","id":"z86NW"},{"name":"pds","id":"D7OZY"},{"name":"pds","id":"e-k9s"},{"name":"pds","id":"CMgAl"},{"name":"beam","class":1,"leftArc":"F","numArcs":6,"id":"tQp4B"},{"name":"beam","class":1,"leftArc":"F","numArcs":6,"id":"1oLgo"},{"name":"beam","class":2,"leftArc":"F","numArcs":6,"id":"_GaL4"},{"name":"beam","class":2,"leftArc":"F","numArcs":6,"id":"5zpxr"}],"ordnance":[],"extras":[],"fighters":[{"name":"fighters","type":"standard","id":"ZqCIV","mods":[],"hangar":"UuT4x"},{"name":"fighters","type":"standard","id":"nn-3Q","mods":[],"hangar":"FuQzk"},{"name":"fighters","type":"standard","id":"0QOJz","mods":[],"hangar":"Dcz5t"},{"name":"fighters","type":"standard","id":"B6yxz","mods":[],"hangar":"-DXfV"},{"name":"fighters","type":"standard","id":"i-ckQ","mods":[],"hangar":"sdszp"},{"name":"fighters","type":"standard","id":"4G0a6","mods":[],"hangar":"atdd3"}],"orientation":"alpha","points":690,"cpv":595,"mass":200,"class":"Fleet Supercarrier","name":"Ark Royal"}
        ]
    },
    {
        "name": "Neu Swabian League (NSL) Kriegsraumflotte",
        "ships": [
            {"hull":{"points":2,"rows":4,"stealth":"0","streamlining":"none"},"armour":[[1,0]],"systems":[{"name":"drive","thrust":6,"advanced":false,"id":"qm5Fg"},{"name":"ftl","advanced":false,"id":"mbE3_"},{"name":"fireControl","id":"Yr-Ab"}],"weapons":[{"name":"beam","class":1,"leftArc":"F","numArcs":6,"id":"OqELP"}],"ordnance":[],"extras":[],"fighters":[],"orientation":"alpha","points":27,"cpv":20,"mass":8,"class":"Scoutship","name":"Falke"},
            {"hull":{"points":4,"rows":4,"stealth":"0","streamlining":"none"},"armour":[[2,0]],"systems":[{"name":"drive","thrust":4,"advanced":false,"id":"QR2hR"},{"name":"ftl","advanced":false,"id":"6GgDp"},{"name":"fireControl","id":"Hl94d"}],"weapons":[{"name":"pds","id":"OdDN-"},{"name":"beam","class":2,"leftArc":"FP","numArcs":3,"id":"3UzQJ"}],"ordnance":[],"extras":[],"fighters":[],"orientation":"alpha","points":47,"cpv":35,"mass":14,"class":"Corvette","name":"Stroschen"},
            {"hull":{"points":6,"rows":4,"stealth":"0","streamlining":"none"},"armour":[[2,0]],"systems":[{"name":"drive","thrust":4,"advanced":false,"id":"_cGQs"},{"name":"ftl","advanced":false,"id":"N2A2P"},{"name":"fireControl","id":"KH2IA"}],"weapons":[{"name":"pds","id":"IWbZY"},{"name":"beam","class":2,"leftArc":"AP","numArcs":3,"id":"v4lF4"},{"name":"beam","class":2,"leftArc":"F","numArcs":3,"id":"Ners_"}],"ordnance":[],"extras":[],"fighters":[],"orientation":"alpha","points":67,"cpv":51,"mass":20,"class":"Frigate","name":"Ehrenhold"},
            {"hull":{"points":9,"rows":4,"stealth":"0","streamlining":"none"},"armour":[[3,0]],"systems":[{"name":"drive","thrust":4,"advanced":false,"id":"qwuOm"},{"name":"ftl","advanced":false,"id":"wtPF9"},{"name":"fireControl","id":"TWe9h"}],"weapons":[{"name":"pds","id":"WWanv"},{"name":"pds","id":"FSodn"},{"name":"beam","class":1,"leftArc":"F","numArcs":6,"id":"FDSIq"},{"name":"beam","class":1,"leftArc":"F","numArcs":6,"id":"IU9IU"},{"name":"beam","class":2,"leftArc":"AP","numArcs":3,"id":"AVKKB"},{"name":"beam","class":2,"leftArc":"F","numArcs":3,"id":"ccWgu"}],"ordnance":[],"extras":[],"fighters":[],"orientation":"alpha","points":100,"cpv":79,"mass":30,"class":"Destroyer","name":"Waldburg"},
            {"hull":{"points":9,"rows":4,"stealth":"0","streamlining":"none"},"armour":[[2,0]],"systems":[{"name":"drive","thrust":4,"advanced":false,"id":"rVnsz"},{"name":"ftl","advanced":false,"id":"U3DYm"},{"name":"magazine","capacity":2,"id":"UbItG"},{"name":"fireControl","id":"FPyeA"}],"weapons":[{"name":"pds","id":"Oa7Cj"},{"name":"beam","class":1,"leftArc":"F","numArcs":6,"id":"lTAi1"}],"ordnance":[{"name":"salvoLauncher","leftArc":"FP","numArcs":3,"id":"LinJ_","magazine":"UbItG"}],"extras":[],"fighters":[],"orientation":"alpha","points":101,"cpv":80,"mass":30,"class":"Missile Destroyer","name":"Waldburg/M"},
            {"hull":{"points":14,"rows":4,"stealth":"0","streamlining":"none"},"armour":[[5,0]],"systems":[{"name":"drive","thrust":4,"advanced":false,"id":"QtyMK"},{"name":"ftl","advanced":false,"id":"u0pAR"},{"name":"adfc","id":"a41E_"},{"name":"fireControl","id":"8zgwk"}],"weapons":[{"name":"pds","id":"jbrT_"},{"name":"pds","id":"o0RJX"},{"name":"pds","id":"9yL6A"},{"name":"beam","class":1,"leftArc":"F","numArcs":6,"id":"aomRS"},{"name":"beam","class":1,"leftArc":"F","numArcs":6,"id":"DK-vZ"},{"name":"beam","class":2,"leftArc":"FP","numArcs":3,"id":"Pfzzs"},{"name":"beam","class":2,"leftArc":"AP","numArcs":3,"id":"TNxCR"},{"name":"beam","class":2,"leftArc":"F","numArcs":3,"id":"hfANq"}],"ordnance":[],"extras":[],"fighters":[],"orientation":"alpha","points":161,"cpv":136,"mass":48,"class":"Light Cruiser","name":"Kronprinz Wilhelm"},
            {"hull":{"points":17,"rows":4,"stealth":"0","streamlining":"none"},"armour":[[6,0]],"systems":[{"name":"drive","thrust":4,"advanced":false,"id":"XyyQ_"},{"name":"ftl","advanced":false,"id":"gwHF5"},{"name":"adfc","id":"abht4"},{"name":"fireControl","id":"KAAWz"},{"name":"fireControl","id":"oF_Ll"}],"weapons":[{"name":"pds","id":"RVkNA"},{"name":"pds","id":"kVwRv"},{"name":"pds","id":"Bpsse"},{"name":"beam","class":1,"leftArc":"F","numArcs":6,"id":"7a1fd"},{"name":"beam","class":1,"leftArc":"F","numArcs":6,"id":"0gFjs"},{"name":"beam","class":2,"leftArc":"FP","numArcs":3,"id":"2zAka"},{"name":"beam","class":2,"leftArc":"FP","numArcs":3,"id":"FIT9t"},{"name":"beam","class":2,"leftArc":"AP","numArcs":3,"id":"fOA_o"},{"name":"beam","class":2,"leftArc":"F","numArcs":3,"id":"1BPog"}],"ordnance":[],"extras":[],"fighters":[],"orientation":"alpha","points":195,"cpv":171,"mass":58,"class":"Escort Cruiser","name":"Radetzky"},
            {"hull":{"points":25,"rows":4,"stealth":"0","streamlining":"none"},"armour":[[10,0]],"systems":[{"name":"drive","thrust":4,"advanced":false,"id":"qsE53"},{"name":"ftl","advanced":false,"id":"pgZjU"},{"name":"fireControl","id":"jeKEW"},{"name":"fireControl","id":"lcci6"}],"weapons":[{"name":"pds","id":"Z5pSs"},{"name":"pds","id":"xxjZV"},{"name":"pds","id":"XVyJ8"},{"name":"beam","class":1,"leftArc":"F","numArcs":6,"id":"tOjXB"},{"name":"beam","class":1,"leftArc":"F","numArcs":6,"id":"RQNDU"},{"name":"beam","class":2,"leftArc":"AP","numArcs":3,"id":"yrggx"},{"name":"beam","class":2,"leftArc":"F","numArcs":3,"id":"Y5Y1d"},{"name":"beam","class":3,"leftArc":"FP","numArcs":3,"id":"G6ix_"},{"name":"beam","class":3,"leftArc":"FP","numArcs":3,"id":"h8ock"}],"ordnance":[],"extras":[],"fighters":[],"orientation":"alpha","points":271,"cpv":256,"mass":82,"class":"Heavy Cruiser","name":"Markgraf"},
            {"hull":{"points":30,"rows":4,"stealth":"0","streamlining":"none"},"armour":[[10,0]],"systems":[{"name":"drive","thrust":4,"advanced":false,"id":"3_zS2"},{"name":"ftl","advanced":false,"id":"IBmsr"},{"name":"fireControl","id":"pCZi5"},{"name":"fireControl","id":"h0afr"},{"name":"fireControl","id":"mVVM3"}],"weapons":[{"name":"pds","id":"7jbiz"},{"name":"pds","id":"g0N84"},{"name":"pds","id":"o8iK8"},{"name":"beam","class":1,"leftArc":"F","numArcs":6,"id":"1pKXi"},{"name":"beam","class":1,"leftArc":"F","numArcs":6,"id":"20C62"},{"name":"beam","class":2,"leftArc":"AP","numArcs":3,"id":"eM9Tp"},{"name":"beam","class":2,"leftArc":"F","numArcs":3,"id":"EP6-8"},{"name":"beam","class":3,"leftArc":"AP","numArcs":3,"id":"TS9SC"},{"name":"beam","class":3,"leftArc":"FP","numArcs":3,"id":"05cFd"},{"name":"beam","class":3,"leftArc":"F","numArcs":3,"id":"3vEsq"}],"ordnance":[],"extras":[],"fighters":[],"orientation":"alpha","points":333,"cpv":333,"mass":100,"class":"Battlecruiser","name":"Maximilian"},
            {"hull":{"points":31,"rows":4,"stealth":"0","streamlining":"none"},"armour":[[6,0]],"systems":[{"name":"drive","thrust":4,"advanced":false,"id":"x2TZk"},{"name":"ftl","advanced":false,"id":"FPqV4"},{"name":"fireControl","id":"zaGbm"},{"name":"fireControl","id":"qnP3d"},{"name":"fireControl","id":"ihO1w"}],"weapons":[{"name":"pds","id":"nMXwR"},{"name":"pds","id":"6nJ65"},{"name":"pds","id":"qoX2G"},{"name":"beam","class":1,"leftArc":"F","numArcs":6,"id":"Y_vK0"},{"name":"beam","class":1,"leftArc":"F","numArcs":6,"id":"PRaty"},{"name":"beam","class":2,"leftArc":"AP","numArcs":3,"id":"f2xNE"},{"name":"beam","class":2,"leftArc":"F","numArcs":3,"id":"3_rBI"},{"name":"beam","class":3,"leftArc":"FP","numArcs":3,"id":"-ZREQ"},{"name":"beam","class":3,"leftArc":"FP","numArcs":3,"id":"q6HZd"},{"name":"beam","class":3,"leftArc":"AP","numArcs":3,"id":"Nwl2n"},{"name":"beam","class":3,"leftArc":"F","numArcs":3,"id":"M1H0u"}],"ordnance":[],"extras":[],"fighters":[],"orientation":"alpha","points":351,"cpv":355,"mass":104,"class":"Battlecruiser","name":"Richthofen"},
            {"hull":{"points":36,"rows":4,"stealth":"0","streamlining":"none"},"armour":[[10,0]],"systems":[{"name":"drive","thrust":2,"advanced":false,"id":"ZM1Ef"},{"name":"ftl","advanced":false,"id":"qypc9"},{"name":"fireControl","id":"8U5ZA"},{"name":"fireControl","id":"ekvqS"},{"name":"fireControl","id":"6vPGb"},{"name":"fireControl","id":"f7jv_"}],"weapons":[{"name":"pds","id":"5i9Mk"},{"name":"pds","id":"amDKe"},{"name":"pds","id":"n9nFL"},{"name":"pds","id":"cepJ8"},{"name":"torpedoPulse","leftArc":"FP","numArcs":3,"id":"Asrp0"},{"name":"beam","class":1,"leftArc":"F","numArcs":6,"id":"4nvJu"},{"name":"beam","class":1,"leftArc":"F","numArcs":6,"id":"86rHH"},{"name":"beam","class":2,"leftArc":"AP","numArcs":3,"id":"6fH8K"},{"name":"beam","class":2,"leftArc":"F","numArcs":3,"id":"WB84n"},{"name":"beam","class":3,"leftArc":"FP","numArcs":3,"id":"6756v"},{"name":"beam","class":3,"leftArc":"AP","numArcs":3,"id":"TOc-a"},{"name":"beam","class":3,"leftArc":"AP","numArcs":3,"id":"4VbRQ"},{"name":"beam","class":3,"leftArc":"F","numArcs":3,"id":"OaxUX"},{"name":"beam","class":3,"leftArc":"F","numArcs":3,"id":"3Fxab"}],"ordnance":[],"extras":[],"fighters":[],"orientation":"alpha","points":414,"cpv":438,"mass":120,"class":"Battleship","name":"Maria Von Burgund"},
            {"hull":{"points":60,"rows":4,"stealth":"0","streamlining":"none"},"armour":[[14,0]],"systems":[{"name":"drive","thrust":2,"advanced":false,"id":"2fUrF"},{"name":"ftl","advanced":false,"id":"6eTF7"},{"name":"hangar","id":"XmKnO","isRack":false,"critRules":false},{"name":"fireControl","id":"LnBgu"},{"name":"fireControl","id":"8__9g"},{"name":"fireControl","id":"TVOFm"},{"name":"fireControl","id":"CQZY8"}],"weapons":[{"name":"pds","id":"y0HqO"},{"name":"pds","id":"7-coh"},{"name":"pds","id":"zziXT"},{"name":"pds","id":"U4OES"},{"name":"beam","class":1,"leftArc":"F","numArcs":6,"id":"e0w0p"},{"name":"beam","class":2,"leftArc":"AP","numArcs":3,"id":"VgLx1"},{"name":"beam","class":2,"leftArc":"F","numArcs":3,"id":"Z5uX5"},{"name":"beam","class":3,"leftArc":"FP","numArcs":3,"id":"uXjIn"},{"name":"beam","class":3,"leftArc":"FP","numArcs":3,"id":"T7wCo"},{"name":"beam","class":3,"leftArc":"AP","numArcs":3,"id":"CcZlw"},{"name":"beam","class":3,"leftArc":"F","numArcs":3,"id":"Iu8DS"}],"ordnance":[],"extras":[],"fighters":[{"name":"fighters","type":"standard","id":"CqRbL","mods":[],"hangar":"XmKnO"}],"orientation":"alpha","points":500,"cpv":531,"mass":150,"class":"Battledreadnought","name":"Szent Istvan"},
            {"hull":{"points":80,"rows":4,"stealth":"0","streamlining":"none"},"armour":[[14,0]],"systems":[{"name":"drive","thrust":2,"advanced":false,"id":"pdXfe"},{"name":"ftl","advanced":false,"id":"HWHMm"},{"name":"fireControl","id":"BwmbB"},{"name":"fireControl","id":"bNDW_"},{"name":"fireControl","id":"x3KBj"},{"name":"fireControl","id":"gKZQI"},{"name":"hangar","id":"UBHuV","isRack":false,"critRules":false},{"name":"magazine","capacity":4,"id":"sFRCT"}],"weapons":[{"name":"pds","id":"uNEbk"},{"name":"pds","id":"0GZD8"},{"name":"pds","id":"BsxEP"},{"name":"pds","id":"9TL-E"},{"name":"beam","class":1,"leftArc":"F","numArcs":6,"id":"4HJQD"},{"name":"beam","class":1,"leftArc":"F","numArcs":6,"id":"_7eZV"},{"name":"beam","class":2,"leftArc":"F","numArcs":6,"id":"iy-_g"},{"name":"beam","class":2,"leftArc":"F","numArcs":6,"id":"zEZfi"},{"name":"beam","class":2,"leftArc":"F","numArcs":6,"id":"wFyO9"},{"name":"beam","class":2,"leftArc":"F","numArcs":6,"id":"bBlgt"},{"name":"beam","class":3,"leftArc":"FP","numArcs":3,"id":"uGZT-"},{"name":"beam","class":3,"leftArc":"FP","numArcs":3,"id":"Db9GQ"},{"name":"beam","class":3,"leftArc":"AP","numArcs":3,"id":"iC-Gs"},{"name":"beam","class":3,"leftArc":"F","numArcs":3,"id":"xxhSS"}],"ordnance":[{"name":"salvoLauncher","leftArc":"FP","numArcs":3,"id":"CLCmo","magazine":"sFRCT"}],"extras":[],"fighters":[{"name":"fighters","type":"standard","id":"cEqlu","mods":[],"hangar":"UBHuV"}],"orientation":"alpha","points":670,"cpv":817,"mass":200,"class":"Superdreadnought","name":"Von Tegetthoff"},
            {"hull":{"points":88,"rows":4,"stealth":"0","streamlining":"none"},"armour":[[14,0]],"systems":[{"name":"drive","thrust":2,"advanced":false,"id":"2-tO4"},{"name":"ftl","advanced":false,"id":"vPvno"},{"name":"fireControl","id":"lwmoa"},{"name":"fireControl","id":"Sucov"},{"name":"fireControl","id":"gxULr"},{"name":"hangar","id":"kjP5u","isRack":false,"critRules":false},{"name":"hangar","id":"Brbph","isRack":false,"critRules":false},{"name":"hangar","id":"VUhca","isRack":false,"critRules":false},{"name":"hangar","id":"3L0rF","isRack":false,"critRules":false}],"weapons":[{"name":"beam","class":1,"leftArc":"F","numArcs":6,"id":"vS4hk"},{"name":"beam","class":1,"leftArc":"F","numArcs":6,"id":"JK11f"},{"name":"beam","class":2,"leftArc":"F","numArcs":6,"id":"Xx9h5"},{"name":"beam","class":2,"leftArc":"F","numArcs":6,"id":"60CL9"},{"name":"beam","class":2,"leftArc":"F","numArcs":6,"id":"PI3ko"},{"name":"beam","class":3,"leftArc":"FS","numArcs":3,"id":"RDth6"},{"name":"beam","class":3,"leftArc":"A","numArcs":3,"id":"_-E2b"},{"name":"beam","class":3,"leftArc":"AS","numArcs":3,"id":"dqUtl"},{"name":"pds","id":"oE3UG"},{"name":"pds","id":"Oy01s"},{"name":"pds","id":"n3xhU"},{"name":"pds","id":"t_UHw"},{"name":"pds","id":"d0eqO"},{"name":"pds","id":"_zxM-"}],"ordnance":[],"extras":[],"fighters":[{"name":"fighters","type":"standard","id":"Bs0qB","mods":[],"hangar":"kjP5u"},{"name":"fighters","type":"standard","id":"r53gV","mods":[],"hangar":"Brbph"},{"name":"fighters","type":"standard","id":"H4xI_","mods":[],"hangar":"VUhca"},{"name":"fighters","type":"standard","id":"TcN__","mods":[],"hangar":"3L0rF"}],"orientation":"alpha","points":737,"cpv":784,"mass":220,"class":"Fighter Carrier","name":"Der Theuerdank"}
        ]
    },
    {
        "name": "L'Astromarine des Federal Stats Europa (FSE)",
        "ships": [
            {"hull":{"points":2,"rows":4,"stealth":"0","streamlining":"none"},"armour":[],"systems":[{"name":"drive","thrust":6,"advanced":false,"id":"Yz8FQ"},{"name":"ftl","advanced":false,"id":"jMcSQ"},{"name":"fireControl","id":"US3q-"}],"weapons":[{"name":"beam","class":1,"leftArc":"F","numArcs":6,"id":"HsyH9"},{"name":"beam","class":1,"leftArc":"F","numArcs":6,"id":"Vd5dI"}],"ordnance":[],"extras":[],"fighters":[],"orientation":"alpha","points":28,"cpv":21,"mass":8,"class":"Scoutship","name":"Mistral"},
            {"hull":{"points":4,"rows":4,"stealth":"0","streamlining":"none"},"armour":[],"systems":[{"name":"drive","thrust":6,"advanced":false,"id":"XeLFe"},{"name":"ftl","advanced":false,"id":"kYJ98"},{"name":"fireControl","id":"38xaN"}],"weapons":[{"name":"pds","id":"CKwir"},{"name":"submunition","leftArc":"FP","numArcs":3,"id":"a9GsO"},{"name":"beam","class":1,"leftArc":"F","numArcs":6,"id":"DOUkL"},{"name":"beam","class":1,"leftArc":"F","numArcs":6,"id":"h7qfY"}],"ordnance":[],"extras":[],"fighters":[],"orientation":"alpha","points":48,"cpv":36,"mass":14,"class":"Corvette","name":"Athena"},
            {"hull":{"points":5,"rows":4,"stealth":"0","streamlining":"none"},"armour":[],"systems":[{"name":"drive","thrust":6,"advanced":false,"id":"fqptY"},{"name":"ftl","advanced":false,"id":"W_XJq"},{"name":"fireControl","id":"dlR4I"}],"weapons":[{"name":"submunition","leftArc":"FP","numArcs":3,"id":"QML8d"},{"name":"submunition","leftArc":"FP","numArcs":3,"id":"4TCsi"},{"name":"pds","id":"BIAgc"},{"name":"beam","class":1,"leftArc":"F","numArcs":6,"id":"CRBcv"},{"name":"beam","class":1,"leftArc":"F","numArcs":6,"id":"IL_Al"}],"ordnance":[],"extras":[],"fighters":[],"orientation":"alpha","points":61,"cpv":46,"mass":18,"class":"Frigate","name":"Ibiza"},
            {"hull":{"points":10,"rows":4,"stealth":"0","streamlining":"none"},"armour":[[2,0]],"systems":[{"name":"drive","thrust":6,"advanced":false,"id":"CPRVM"},{"name":"ftl","advanced":false,"id":"bieYi"},{"name":"fireControl","id":"jzot2"}],"weapons":[{"name":"pds","id":"ytc3d"},{"name":"pds","id":"1ACMa"},{"name":"beam","class":1,"leftArc":"F","numArcs":6,"id":"fZyIs"},{"name":"beam","class":1,"leftArc":"F","numArcs":6,"id":"O3plU"},{"name":"beam","class":2,"leftArc":"AP","numArcs":3,"id":"pvi04"},{"name":"beam","class":2,"leftArc":"F","numArcs":3,"id":"BNklL"}],"ordnance":[],"extras":[],"fighters":[],"orientation":"alpha","points":112,"cpv":90,"mass":34,"class":"Destroyer","name":"San Miguel"},
            {"hull":{"points":13,"rows":4,"stealth":"0","streamlining":"none"},"armour":[],"systems":[{"name":"drive","thrust":6,"advanced":false,"id":"_Fy-1"},{"name":"ftl","advanced":false,"id":"fX2WB"},{"name":"fireControl","id":"2m86Y"},{"name":"magazine","capacity":2,"id":"zUNTL"}],"weapons":[{"name":"pds","id":"hUqM1"},{"name":"beam","class":1,"leftArc":"F","numArcs":6,"id":"_IZ-4"},{"name":"beam","class":2,"leftArc":"FP","numArcs":3,"id":"S4_8r"}],"ordnance":[{"name":"salvoLauncher","leftArc":"FP","numArcs":3,"id":"4eD5J","magazine":"zUNTL"}],"extras":[],"fighters":[],"orientation":"alpha","points":139,"cpv":115,"mass":42,"class":"Super Destroyer","name":"Trieste"},
            {"hull":{"points":16,"rows":4,"stealth":"0","streamlining":"none"},"armour":[],"systems":[{"name":"drive","thrust":6,"advanced":false,"id":"nfcU_"},{"name":"ftl","advanced":false,"id":"rVd5N"},{"name":"fireControl","id":"RcIjT"},{"name":"fireControl","id":"nGv7z"},{"name":"magazine","capacity":3,"id":"g9yla"}],"weapons":[{"name":"pds","id":"tUmd6"},{"name":"pds","id":"8TF_d"},{"name":"beam","class":2,"leftArc":"AP","numArcs":3,"id":"Tljso"},{"name":"beam","class":2,"leftArc":"F","numArcs":3,"id":"eAnNG"}],"ordnance":[{"name":"salvoLauncher","leftArc":"FP","numArcs":3,"id":"o64Hg","magazine":"g9yla"}],"extras":[],"fighters":[],"orientation":"alpha","points":181,"cpv":156,"mass":54,"class":"Light Cruiser","name":"Suffren"},
            {"hull":{"points":19,"rows":4,"stealth":"0","streamlining":"none"},"armour":[],"systems":[{"name":"drive","thrust":6,"advanced":false,"id":"beo-M"},{"name":"ftl","advanced":false,"id":"fEDX7"},{"name":"fireControl","id":"mx4BY"},{"name":"fireControl","id":"XUBXz"},{"name":"magazine","capacity":3,"id":"4CE3H"}],"weapons":[{"name":"pds","id":"tY55x"},{"name":"pds","id":"1JuZZ"},{"name":"beam","class":1,"leftArc":"F","numArcs":6,"id":"CnbgE"},{"name":"beam","class":2,"leftArc":"AP","numArcs":3,"id":"dW58a"},{"name":"beam","class":2,"leftArc":"F","numArcs":3,"id":"4jjYz"}],"ordnance":[{"name":"salvoLauncher","leftArc":"FP","numArcs":3,"id":"sQeyl","magazine":"4CE3H"}],"extras":[],"fighters":[],"orientation":"alpha","points":206,"cpv":182,"mass":62,"class":"Escort Cruiser","name":"Milan"},
            {"hull":{"points":26,"rows":4,"stealth":"0","streamlining":"none"},"armour":[],"systems":[{"name":"drive","thrust":6,"advanced":false,"id":"1WDhS"},{"name":"ftl","advanced":false,"id":"wXd4D"},{"name":"fireControl","id":"t_3n3"},{"name":"fireControl","id":"X4H2q"},{"name":"magazine","capacity":4,"id":"4WuU_"}],"weapons":[{"name":"pds","id":"mC62p"},{"name":"pds","id":"wI_I8"},{"name":"beam","class":1,"leftArc":"F","numArcs":6,"id":"L4ls9"},{"name":"beam","class":1,"leftArc":"F","numArcs":6,"id":"wMSkG"},{"name":"beam","class":2,"leftArc":"F","numArcs":6,"id":"vn4oL"},{"name":"beam","class":2,"leftArc":"AP","numArcs":3,"id":"fh1AL"},{"name":"beam","class":2,"leftArc":"F","numArcs":3,"id":"MJyXh"}],"ordnance":[{"name":"salvoLauncher","leftArc":"FP","numArcs":3,"id":"Wg28R","magazine":"4WuU_"},{"name":"salvoLauncher","leftArc":"FP","numArcs":3,"id":"VAnnh","magazine":"4WuU_"}],"extras":[],"fighters":[],"orientation":"alpha","points":293,"cpv":282,"mass":88,"class":"Heavy Cruiser","name":"Jerez"},
            {"hull":{"points":29,"rows":4,"stealth":"0","streamlining":"none"},"armour":[],"systems":[{"name":"drive","thrust":6,"advanced":false,"id":"_XD8W"},{"name":"ftl","advanced":false,"id":"gvNrm"},{"name":"fireControl","id":"yaNag"},{"name":"fireControl","id":"wW2cJ"},{"name":"screen","area":false,"advanced":false,"id":"I3CwG"},{"name":"magazine","capacity":3,"id":"yA27U"}],"weapons":[{"name":"pds","id":"nyLyp"},{"name":"pds","id":"u4-h7"},{"name":"pds","id":"plTo1"},{"name":"beam","class":1,"leftArc":"F","numArcs":6,"id":"4RmFS"},{"name":"beam","class":1,"leftArc":"F","numArcs":6,"id":"Ha93S"},{"name":"beam","class":2,"leftArc":"F","numArcs":6,"id":"F3k4O"},{"name":"beam","class":2,"leftArc":"AP","numArcs":3,"id":"OfKeb"},{"name":"beam","class":2,"leftArc":"F","numArcs":3,"id":"pAQIj"}],"ordnance":[{"name":"salvoLauncher","leftArc":"FP","numArcs":3,"id":"WB5PE","magazine":"yA27U"}],"extras":[],"fighters":[],"orientation":"alpha","points":318,"cpv":314,"mass":96,"class":"Battlecruiser","name":"Ypres"},
            {"hull":{"points":33,"rows":4,"stealth":"0","streamlining":"none"},"armour":[],"systems":[{"name":"drive","thrust":4,"advanced":false,"id":"i8stG"},{"name":"ftl","advanced":false,"id":"LBP-E"},{"name":"fireControl","id":"aiHlx"},{"name":"fireControl","id":"2gpvq"},{"name":"fireControl","id":"rwjVU"},{"name":"magazine","capacity":6,"id":"3FcxX"},{"name":"screen","area":false,"advanced":false,"id":"nWP8W"}],"weapons":[{"name":"pds","id":"mggMh"},{"name":"pds","id":"huKiO"},{"name":"pds","id":"1ft3L"},{"name":"pds","id":"-4zMD"},{"name":"beam","class":1,"leftArc":"F","numArcs":6,"id":"GPRPp"},{"name":"beam","class":1,"leftArc":"F","numArcs":6,"id":"8f8CQ"},{"name":"beam","class":2,"leftArc":"F","numArcs":6,"id":"OVjJn"},{"name":"beam","class":2,"leftArc":"AP","numArcs":3,"id":"_Obf3"},{"name":"beam","class":2,"leftArc":"AP","numArcs":3,"id":"aB9fW"},{"name":"beam","class":2,"leftArc":"F","numArcs":3,"id":"u4xuL"},{"name":"beam","class":2,"leftArc":"F","numArcs":3,"id":"m8wyA"}],"ordnance":[{"name":"salvoLauncher","leftArc":"AP","numArcs":3,"id":"Ae_b8","magazine":"3FcxX"},{"name":"salvoLauncher","leftArc":"F","numArcs":3,"id":"2XUB2","magazine":"3FcxX"}],"extras":[],"fighters":[],"orientation":"alpha","points":377,"cpv":388,"mass":110,"class":"Battlecruiser","name":"Roma"},
            {"hull":{"points":48,"rows":4,"stealth":"0","streamlining":"none"},"armour":[],"systems":[{"name":"drive","thrust":6,"advanced":false,"id":"szjMP"},{"name":"ftl","advanced":false,"id":"jVTzJ"},{"name":"fireControl","id":"ariG-"},{"name":"fireControl","id":"-sBNf"},{"name":"fireControl","id":"VNmyn"},{"name":"screen","area":false,"advanced":false,"id":"nGmec"},{"name":"hangar","id":"FuiKW","isRack":false,"critRules":false},{"name":"magazine","capacity":4,"id":"F1EtI"}],"weapons":[{"name":"pds","id":"8t67W"},{"name":"pds","id":"cuHqH"},{"name":"pds","id":"mQooO"},{"name":"pds","id":"JB0Mc"},{"name":"beam","class":1,"leftArc":"F","numArcs":6,"id":"zd5j5"},{"name":"beam","class":1,"leftArc":"F","numArcs":6,"id":"J5Jaw"},{"name":"beam","class":2,"leftArc":"F","numArcs":6,"id":"PmaeJ"},{"name":"beam","class":2,"leftArc":"AP","numArcs":3,"id":"F9D20"},{"name":"beam","class":2,"leftArc":"F","numArcs":3,"id":"CpBAe"},{"name":"beam","class":3,"leftArc":"F","numArcs":1,"id":"Tkewo"}],"ordnance":[{"name":"salvoLauncher","leftArc":"FP","numArcs":3,"id":"2Xz2I","magazine":"F1EtI"}],"extras":[],"fighters":[{"name":"fighters","type":"standard","id":"gmJpi","mods":[],"hangar":"FuiKW"}],"orientation":"alpha","points":531,"cpv":581,"mass":160,"class":"Battledreadnought","name":"Bonaparte"},
            {"hull":{"points":75,"rows":4,"stealth":"0","streamlining":"none"},"armour":[],"systems":[{"name":"drive","thrust":4,"advanced":false,"id":"eH_JB"},{"name":"ftl","advanced":false,"id":"ET89M"},{"name":"fireControl","id":"G-7TD"},{"name":"fireControl","id":"ojJhx"},{"name":"fireControl","id":"9VlFj"},{"name":"fireControl","id":"a7nTe"},{"name":"fireControl","id":"kI1gG"},{"name":"screen","area":false,"advanced":false,"id":"kjM0R"},{"name":"hangar","id":"qiDeF","isRack":false,"critRules":false},{"name":"hangar","id":"es89J","isRack":false,"critRules":false},{"name":"hangar","id":"pRo_s","isRack":false,"critRules":false},{"name":"magazine","capacity":9,"id":"WBYMi"}],"weapons":[{"name":"pds","id":"KoLl-"},{"name":"pds","id":"N5Uqp"},{"name":"pds","id":"94Uji"},{"name":"pds","id":"QEd_B"},{"name":"pds","id":"yh1Pv"},{"name":"pds","id":"yAaTe"},{"name":"beam","class":2,"leftArc":"F","numArcs":6,"id":"uyn51"},{"name":"beam","class":2,"leftArc":"F","numArcs":6,"id":"_wjku"},{"name":"beam","class":2,"leftArc":"AP","numArcs":3,"id":"IfDCJ"},{"name":"beam","class":2,"leftArc":"F","numArcs":3,"id":"IaxsV"},{"name":"beam","class":3,"leftArc":"FP","numArcs":3,"id":"quG2h"},{"name":"beam","class":3,"leftArc":"FP","numArcs":3,"id":"SFMB4"}],"ordnance":[{"name":"salvoLauncher","leftArc":"FP","numArcs":3,"id":"QETBJ","magazine":"WBYMi"},{"name":"salvoLauncher","leftArc":"AP","numArcs":3,"id":"aVhUS","magazine":"WBYMi"},{"name":"salvoLauncher","leftArc":"F","numArcs":3,"id":"p-TiQ","magazine":"WBYMi"}],"extras":[],"fighters":[{"name":"fighters","type":"standard","id":"dWNuS","mods":[],"hangar":"qiDeF"},{"name":"fighters","type":"standard","id":"2JslA","mods":[],"hangar":"es89J"},{"name":"fighters","type":"standard","id":"LlQym","mods":[],"hangar":"pRo_s"}],"orientation":"alpha","points":855,"cpv":1048,"mass":250,"class":"Superdreadnought","name":"Foch"},
            {"hull":{"points":51,"rows":4,"stealth":"0","streamlining":"none"},"armour":[],"systems":[{"name":"drive","thrust":4,"advanced":false,"id":"IIYt1"},{"name":"ftl","advanced":false,"id":"4-XIq"},{"name":"fireControl","id":"uSzVj"},{"name":"fireControl","id":"ErllU"},{"name":"screen","area":false,"advanced":false,"id":"NCrkK"},{"name":"magazine","capacity":3,"id":"D_nSJ"},{"name":"hangar","id":"e66d7","isRack":false,"critRules":false},{"name":"hangar","id":"LvidC","isRack":false,"critRules":false},{"name":"hangar","id":"XEeRo","isRack":false,"critRules":false},{"name":"hangar","id":"KVvon","isRack":false,"critRules":false}],"weapons":[{"name":"pds","id":"Coe2u"},{"name":"pds","id":"S0oaV"},{"name":"pds","id":"R4Sux"},{"name":"pds","id":"lvJmK"},{"name":"beam","class":1,"leftArc":"F","numArcs":6,"id":"BgUeK"},{"name":"beam","class":1,"leftArc":"F","numArcs":6,"id":"FhfRP"},{"name":"beam","class":2,"leftArc":"F","numArcs":6,"id":"QshEj"},{"name":"beam","class":2,"leftArc":"F","numArcs":6,"id":"d0DxI"}],"ordnance":[{"name":"salvoLauncher","leftArc":"FP","numArcs":3,"id":"l73LW","magazine":"D_nSJ"}],"extras":[],"fighters":[{"name":"fighters","type":"standard","id":"70dSJ","mods":[],"hangar":"e66d7"},{"name":"fighters","type":"standard","id":"diDRw","mods":[],"hangar":"LvidC"},{"name":"fighters","type":"standard","id":"0JVvn","mods":[],"hangar":"XEeRo"},{"name":"fighters","type":"standard","id":"lu_ud","mods":[],"hangar":"KVvon"}],"orientation":"alpha","points":580,"cpv":518,"mass":170,"class":"Light Carrier","name":"Bologna"},
            {"hull":{"points":84,"rows":4,"stealth":"0","streamlining":"none"},"armour":[],"systems":[{"name":"drive","thrust":4,"advanced":false,"id":"65oYF"},{"name":"ftl","advanced":false,"id":"uLrB-"},{"name":"fireControl","id":"8lzkR"},{"name":"fireControl","id":"SVO3b"},{"name":"fireControl","id":"_CXcS"},{"name":"magazine","capacity":3,"id":"2OHGI"},{"name":"screen","area":false,"advanced":false,"id":"uwID-"},{"name":"hangar","id":"LEAsk","isRack":false,"critRules":false},{"name":"hangar","id":"asxqB","isRack":false,"critRules":false},{"name":"hangar","id":"x6pKZ","isRack":false,"critRules":false},{"name":"hangar","id":"bam0j","isRack":false,"critRules":false},{"name":"hangar","id":"nGfFy","isRack":false,"critRules":false},{"name":"hangar","id":"mahqz","isRack":false,"critRules":false},{"name":"hangar","id":"dtE7K","isRack":false,"critRules":false}],"weapons":[{"name":"pds","id":"GJXy9"},{"name":"pds","id":"7VXCH"},{"name":"pds","id":"0bBR0"},{"name":"pds","id":"kmxua"},{"name":"pds","id":"whL-d"},{"name":"pds","id":"nvuab"},{"name":"beam","class":2,"leftArc":"F","numArcs":6,"id":"dzJBJ"},{"name":"beam","class":2,"leftArc":"FP","numArcs":3,"id":"vlmqb"},{"name":"beam","class":3,"leftArc":"FP","numArcs":3,"id":"6mvZN"},{"name":"beam","class":3,"leftArc":"FP","numArcs":3,"id":"oDkLj"}],"ordnance":[{"name":"salvoLauncher","leftArc":"FP","numArcs":3,"id":"gmfhm","magazine":"2OHGI"}],"extras":[],"fighters":[{"name":"fighters","type":"standard","id":"khsae","mods":[],"hangar":"LEAsk"},{"name":"fighters","type":"standard","id":"B6-Gl","mods":[],"hangar":"asxqB"},{"name":"fighters","type":"standard","id":"O_D2U","mods":[],"hangar":"x6pKZ"},{"name":"fighters","type":"standard","id":"m-spe","mods":[],"hangar":"bam0j"},{"name":"fighters","type":"standard","id":"fTVl5","mods":[],"hangar":"nGfFy"},{"name":"fighters","type":"standard","id":"ooCGU","mods":[],"hangar":"mahqz"},{"name":"fighters","type":"standard","id":"kahAb","mods":[],"hangar":"dtE7K"}],"orientation":"alpha","points":955,"cpv":1020,"mass":280,"class":"Fleet Carrier","name":"Jeanne D'Arc"}
        ]
    },
    {
        "name": "Eurasian Solar Union (ESU) Voyenno Kosmicheskiy Flot",
        "ships": [
            {"hull":{"points":1,"rows":4,"stealth":"0","streamlining":"none"},"armour":[],"systems":[{"name":"drive","thrust":8,"advanced":false,"id":"p16c1"},{"name":"ftl","advanced":false,"id":"5EpIZ"},{"name":"fireControl","id":"3x3BK"}],"weapons":[{"name":"beam","class":1,"leftArc":"F","numArcs":6,"id":"0yW2p"}],"ordnance":[],"extras":[],"fighters":[],"orientation":"alpha","points":21,"cpv":16,"mass":6,"class":"Scoutship","name":"Lenov"},
            {"hull":{"points":4,"rows":4,"stealth":"0","streamlining":"none"},"armour":[],"systems":[{"name":"drive","thrust":6,"advanced":false,"id":"cxPNI"},{"name":"ftl","advanced":false,"id":"Xr-c4"},{"name":"fireControl","id":"0WS6X"}],"weapons":[{"name":"pds","id":"gONq-"},{"name":"beam","class":1,"leftArc":"F","numArcs":6,"id":"AvFi4"},{"name":"beam","class":2,"leftArc":"FP","numArcs":3,"id":"o0yjb"}],"ordnance":[],"extras":[],"fighters":[],"orientation":"alpha","points":48,"cpv":36,"mass":14,"class":"Corvette","name":"Nanuchka II"},
            {"hull":{"points":7,"rows":4,"stealth":"0","streamlining":"none"},"armour":[],"systems":[{"name":"drive","thrust":6,"advanced":false,"id":"7FRtN"},{"name":"ftl","advanced":false,"id":"I_8zf"},{"name":"fireControl","id":"AflQN"}],"weapons":[{"name":"pds","id":"oQPjU"},{"name":"beam","class":1,"leftArc":"F","numArcs":6,"id":"eSPSk"},{"name":"beam","class":1,"leftArc":"F","numArcs":6,"id":"nzlmK"},{"name":"beam","class":2,"leftArc":"FP","numArcs":3,"id":"3dKoY"}],"ordnance":[],"extras":[],"fighters":[],"orientation":"alpha","points":73,"cpv":56,"mass":22,"class":"Frigate","name":"Novgorod"},
            {"hull":{"points":8,"rows":4,"stealth":"0","streamlining":"none"},"armour":[[3,0]],"systems":[{"name":"drive","thrust":4,"advanced":false,"id":"vSTzW"},{"name":"ftl","advanced":false,"id":"SxEFP"},{"name":"fireControl","id":"PRP4O"}],"weapons":[{"name":"pds","id":"4wEox"},{"name":"beam","class":1,"leftArc":"F","numArcs":6,"id":"xAm9E"},{"name":"beam","class":1,"leftArc":"F","numArcs":6,"id":"3dxcE"},{"name":"beam","class":2,"leftArc":"AP","numArcs":3,"id":"Njtke"},{"name":"beam","class":2,"leftArc":"F","numArcs":3,"id":"ek2Qm"}],"ordnance":[],"extras":[],"fighters":[],"orientation":"alpha","points":93,"cpv":73,"mass":28,"class":"Destroyer","name":"Warsaw"},
            {"hull":{"points":10,"rows":4,"stealth":"0","streamlining":"none"},"armour":[[2,0]],"systems":[{"name":"drive","thrust":4,"advanced":false,"id":"hLFIt"},{"name":"ftl","advanced":false,"id":"xbvEm"},{"name":"fireControl","id":"ARRol"}],"weapons":[{"name":"pds","id":"H-rW5"},{"name":"beam","class":1,"leftArc":"F","numArcs":6,"id":"ld6vG"},{"name":"beam","class":1,"leftArc":"F","numArcs":6,"id":"Pvvk3"},{"name":"beam","class":2,"leftArc":"F","numArcs":6,"id":"DMeIk"},{"name":"beam","class":2,"leftArc":"AP","numArcs":3,"id":"nEPfe"},{"name":"beam","class":2,"leftArc":"F","numArcs":3,"id":"tKmNB"},{"name":"pds","id":"CdCln"}],"ordnance":[],"extras":[],"fighters":[],"orientation":"alpha","points":115,"cpv":93,"mass":34,"class":"Super Destroyer","name":"Volga"},
            {"hull":{"points":14,"rows":4,"stealth":"0","streamlining":"none"},"armour":[[3,0]],"systems":[{"name":"drive","thrust":4,"advanced":false,"id":"HfeuQ"},{"name":"ftl","advanced":false,"id":"Tba6C"},{"name":"screen","area":false,"advanced":false,"id":"7yNJZ"},{"name":"fireControl","id":"6vzn5"},{"name":"fireControl","id":"UvAtA"}],"weapons":[{"name":"pds","id":"unlYz"},{"name":"pds","id":"4WKtE"},{"name":"beam","class":1,"leftArc":"F","numArcs":6,"id":"jnIIB"},{"name":"beam","class":1,"leftArc":"F","numArcs":6,"id":"dR03K"},{"name":"beam","class":2,"leftArc":"F","numArcs":6,"id":"EdvRF"},{"name":"beam","class":2,"leftArc":"AP","numArcs":3,"id":"UHf2h"},{"name":"beam","class":2,"leftArc":"F","numArcs":3,"id":"OSG8s"}],"ordnance":[],"extras":[],"fighters":[],"orientation":"alpha","points":162,"cpv":137,"mass":48,"class":"Light Cruiser","name":"Tibet"},
            {"hull":{"points":18,"rows":4,"stealth":"0","streamlining":"none"},"armour":[[5,0]],"systems":[{"name":"drive","thrust":4,"advanced":false,"id":"Amjp8"},{"name":"ftl","advanced":false,"id":"ozZru"},{"name":"fireControl","id":"djA7V"},{"name":"fireControl","id":"fc3BL"},{"name":"screen","area":false,"advanced":false,"id":"YVyVt"}],"weapons":[{"name":"pds","id":"TEtmk"},{"name":"pds","id":"B7JIl"},{"name":"beam","class":1,"leftArc":"F","numArcs":6,"id":"r6GN-"},{"name":"beam","class":1,"leftArc":"F","numArcs":6,"id":"H4-h9"},{"name":"beam","class":2,"leftArc":"AP","numArcs":3,"id":"Lp74Q"},{"name":"beam","class":2,"leftArc":"F","numArcs":3,"id":"Y5muT"},{"name":"beam","class":3,"leftArc":"FP","numArcs":3,"id":"FAho3"}],"ordnance":[],"extras":[],"fighters":[],"orientation":"alpha","points":201,"cpv":177,"mass":60,"class":"Escort Cruiser","name":"Beijing/B"},
            {"hull":{"points":21,"rows":4,"stealth":"0","streamlining":"none"},"armour":[],"systems":[{"name":"drive","thrust":4,"advanced":false,"id":"A23Cy"},{"name":"ftl","advanced":false,"id":"lWfGl"},{"name":"screen","area":false,"advanced":false,"id":"PUS2D"},{"name":"fireControl","id":"369Vg"},{"name":"fireControl","id":"e0gye"}],"weapons":[{"name":"pds","id":"je4wj"},{"name":"pds","id":"VUfwp"},{"name":"beam","class":1,"leftArc":"F","numArcs":6,"id":"RNeX8"},{"name":"beam","class":1,"leftArc":"F","numArcs":6,"id":"5yeRM"},{"name":"beam","class":2,"leftArc":"AP","numArcs":3,"id":"LrEPi"},{"name":"beam","class":2,"leftArc":"F","numArcs":3,"id":"GL7f3"},{"name":"beam","class":3,"leftArc":"FP","numArcs":3,"id":"Tjlui"}],"ordnance":[{"name":"salvo","id":"hde0C"},{"name":"salvo","id":"F6QLY"}],"extras":[],"fighters":[],"orientation":"alpha","points":240,"cpv":219,"mass":70,"class":"Heavy Cruiser","name":"Gorshkov"},
            {"hull":{"points":23,"rows":4,"stealth":"0","streamlining":"none"},"armour":[[5,0]],"systems":[{"name":"drive","thrust":4,"advanced":false,"id":"vE7zD"},{"name":"ftl","advanced":false,"id":"hlsaH"},{"name":"screen","area":false,"advanced":false,"id":"a7F5d"},{"name":"fireControl","id":"PVK1_"},{"name":"fireControl","id":"gGfql"}],"weapons":[{"name":"pds","id":"9h8tr"},{"name":"pds","id":"Eq2ip"},{"name":"beam","class":1,"leftArc":"F","numArcs":6,"id":"bEC1b"},{"name":"beam","class":1,"leftArc":"F","numArcs":6,"id":"3c4WY"},{"name":"beam","class":2,"leftArc":"AP","numArcs":3,"id":"LSIls"},{"name":"beam","class":2,"leftArc":"F","numArcs":3,"id":"hOSc8"},{"name":"beam","class":3,"leftArc":"FP","numArcs":3,"id":"YkxS0"},{"name":"beam","class":3,"leftArc":"FP","numArcs":3,"id":"UI8XP"}],"ordnance":[],"extras":[],"fighters":[],"orientation":"alpha","points":262,"cpv":245,"mass":78,"class":"Heavy Cruiser","name":"Voroshilev"},
            {"hull":{"points":38,"rows":4,"stealth":"0","streamlining":"none"},"armour":[],"systems":[{"name":"drive","thrust":4,"advanced":false,"id":"NCTIg"},{"name":"ftl","advanced":false,"id":"f40_N"},{"name":"screen","area":false,"advanced":false,"id":"Xtn5M"},{"name":"fireControl","id":"feje3"},{"name":"fireControl","id":"ePSuJ"}],"weapons":[{"name":"pds","id":"jjT5e"},{"name":"pds","id":"4Ha2x"},{"name":"beam","class":1,"leftArc":"F","numArcs":6,"id":"uhrsN"},{"name":"beam","class":2,"leftArc":"AP","numArcs":3,"id":"9FfHA"},{"name":"beam","class":2,"leftArc":"FP","numArcs":3,"id":"iHeqP"},{"name":"beam","class":2,"leftArc":"F","numArcs":3,"id":"bvCAg"},{"name":"beam","class":3,"leftArc":"FP","numArcs":3,"id":"TFXp6"},{"name":"beam","class":3,"leftArc":"FP","numArcs":3,"id":"ncjZO"}],"ordnance":[],"extras":[],"fighters":[],"orientation":"alpha","points":312,"cpv":306,"mass":94,"class":"Battlecruiser","name":"Manchuria"},
            {"hull":{"points":46,"rows":4,"stealth":"0","streamlining":"none"},"armour":[],"systems":[{"name":"drive","thrust":4,"advanced":false,"id":"2eFIk"},{"name":"ftl","advanced":false,"id":"cIAcL"},{"name":"screen","area":false,"advanced":false,"id":"oadD4"},{"name":"fireControl","id":"2y17P"},{"name":"fireControl","id":"korqi"},{"name":"fireControl","id":"Jg3Ev"}],"weapons":[{"name":"pds","id":"CDjHj"},{"name":"pds","id":"7A2d3"},{"name":"pds","id":"mGCQ_"},{"name":"beam","class":1,"leftArc":"F","numArcs":6,"id":"HULvG"},{"name":"beam","class":1,"leftArc":"F","numArcs":6,"id":"DSdBp"},{"name":"beam","class":1,"leftArc":"F","numArcs":6,"id":"G142L"},{"name":"beam","class":2,"leftArc":"AP","numArcs":3,"id":"cFAX1"},{"name":"beam","class":2,"leftArc":"FP","numArcs":3,"id":"AZndk"},{"name":"beam","class":2,"leftArc":"FP","numArcs":3,"id":"ZqyPf"},{"name":"beam","class":2,"leftArc":"F","numArcs":3,"id":"usvYY"},{"name":"beam","class":3,"leftArc":"FP","numArcs":3,"id":"4-MJI"},{"name":"beam","class":3,"leftArc":"FP","numArcs":3,"id":"KvJc8"}],"ordnance":[],"extras":[],"fighters":[],"orientation":"alpha","points":386,"cpv":405,"mass":116,"class":"Battleship","name":"Petrograd"},
            {"hull":{"points":55,"rows":4,"stealth":"0","streamlining":"none"},"armour":[],"systems":[{"name":"drive","thrust":4,"advanced":false,"id":"FwPjE"},{"name":"ftl","advanced":false,"id":"3M4Ck"},{"name":"screen","area":false,"advanced":false,"id":"daTcH"},{"name":"fireControl","id":"jp83p"},{"name":"fireControl","id":"XE56o"},{"name":"fireControl","id":"ZzWd-"},{"name":"hangar","id":"XMhLh","isRack":false,"critRules":false}],"weapons":[{"name":"pds","id":"gnsfO"},{"name":"pds","id":"NCAZl"},{"name":"pds","id":"Ru08T"},{"name":"beam","class":1,"leftArc":"F","numArcs":6,"id":"6P1q5"},{"name":"beam","class":2,"leftArc":"AP","numArcs":3,"id":"mi4n_"},{"name":"beam","class":2,"leftArc":"FP","numArcs":3,"id":"Te1S4"},{"name":"beam","class":2,"leftArc":"F","numArcs":3,"id":"Gwi-l"},{"name":"beam","class":3,"leftArc":"AP","numArcs":3,"id":"3zRDj"},{"name":"beam","class":3,"leftArc":"F","numArcs":3,"id":"mgjLa"}],"ordnance":[],"extras":[],"fighters":[],"orientation":"alpha","points":458,"cpv":468,"mass":138,"class":"Battledreadnought","name":"Rostov"},
            {"hull":{"points":45,"rows":4,"stealth":"0","streamlining":"none"},"armour":[],"systems":[{"name":"drive","thrust":4,"advanced":false,"id":"JRFf7"},{"name":"ftl","advanced":false,"id":"EOkiJ"},{"name":"screen","area":false,"advanced":false,"id":"i-1nB"},{"name":"fireControl","id":"qbXOu"},{"name":"fireControl","id":"naPGW"},{"name":"hangar","id":"oAqxC","isRack":false,"critRules":false},{"name":"hangar","id":"7ifyb","isRack":false,"critRules":false},{"name":"hangar","id":"NySjV","isRack":false,"critRules":false},{"name":"hangar","id":"nQa_x","isRack":false,"critRules":false}],"weapons":[{"name":"pds","id":"cNWAH"},{"name":"pds","id":"EfH9j"},{"name":"pds","id":"nWvdk"},{"name":"pds","id":"z0Bjy"},{"name":"beam","class":1,"leftArc":"F","numArcs":6,"id":"xDZhd"},{"name":"beam","class":1,"leftArc":"F","numArcs":6,"id":"u1fsQ"},{"name":"beam","class":2,"leftArc":"AP","numArcs":3,"id":"hOmtV"},{"name":"beam","class":2,"leftArc":"FP","numArcs":3,"id":"Q0Wr2"},{"name":"beam","class":2,"leftArc":"FP","numArcs":3,"id":"qhi22"},{"name":"beam","class":2,"leftArc":"F","numArcs":3,"id":"ojFPn"}],"ordnance":[],"extras":[],"fighters":[{"name":"fighters","type":"standard","id":"t7DIn","mods":[],"hangar":"oAqxC"},{"name":"fighters","type":"standard","id":"YKK4F","mods":[],"hangar":"7ifyb"},{"name":"fighters","type":"standard","id":"ay_ZY","mods":[],"hangar":"NySjV"},{"name":"fighters","type":"standard","id":"YKURq","mods":[],"hangar":"nQa_x"}],"orientation":"alpha","points":512,"cpv":420,"mass":150,"class":"Light Carrier","name":"Tsiolkovsky"},
            {"hull":{"points":88,"rows":4,"stealth":"0","streamlining":"none"},"armour":[],"systems":[{"name":"drive","thrust":2,"advanced":false,"id":"b0Txi"},{"name":"ftl","advanced":false,"id":"uupO_"},{"name":"screen","area":false,"advanced":false,"id":"0l0gu"},{"name":"screen","area":false,"advanced":false,"id":"cjqwy"},{"name":"fireControl","id":"MvjD7"},{"name":"fireControl","id":"M4qe4"},{"name":"fireControl","id":"WAbnT"},{"name":"hangar","id":"WD304","isRack":false,"critRules":false}],"weapons":[{"name":"pds","id":"Sc22X"},{"name":"pds","id":"x8k9q"},{"name":"pds","id":"apSP_"},{"name":"pds","id":"LVPoh"},{"name":"beam","class":1,"leftArc":"F","numArcs":6,"id":"0CiJu"},{"name":"beam","class":1,"leftArc":"F","numArcs":6,"id":"dGsSg"},{"name":"beam","class":2,"leftArc":"AP","numArcs":3,"id":"l6bCb"},{"name":"beam","class":2,"leftArc":"F","numArcs":3,"id":"KCDhF"},{"name":"beam","class":3,"leftArc":"AP","numArcs":3,"id":"Nb4mc"},{"name":"beam","class":3,"leftArc":"FP","numArcs":3,"id":"FrCzj"},{"name":"beam","class":3,"leftArc":"FP","numArcs":3,"id":"1n7Il"},{"name":"beam","class":3,"leftArc":"F","numArcs":3,"id":"lxZQU"},{"name":"beam","class":4,"leftArc":"FP","numArcs":2,"id":"jbnF-"},{"name":"beam","class":4,"leftArc":"F","numArcs":2,"id":"61q-Y"}],"ordnance":[],"extras":[],"fighters":[{"name":"fighters","type":"standard","id":"FOXY-","mods":[],"hangar":"WD304"}],"orientation":"alpha","points":751,"cpv":958,"mass":220,"class":"Superdreadnought","name":"Komarov"},
            {"hull":{"points":72,"rows":4,"stealth":"0","streamlining":"none"},"armour":[],"systems":[{"name":"drive","thrust":2,"advanced":false,"id":"q7Leg"},{"name":"ftl","advanced":false,"id":"ldkgq"},{"name":"screen","area":false,"advanced":false,"id":"xv2qU"},{"name":"screen","area":false,"advanced":false,"id":"ZqYDP"},{"name":"fireControl","id":"mdpi2"},{"name":"fireControl","id":"IqDbI"},{"name":"hangar","id":"EQ2W6","isRack":false,"critRules":false},{"name":"hangar","id":"sw_ET","isRack":false,"critRules":false},{"name":"hangar","id":"DRonE","isRack":false,"critRules":false},{"name":"hangar","id":"5hxLH","isRack":false,"critRules":false},{"name":"hangar","id":"FJl7X","isRack":false,"critRules":false},{"name":"hangar","id":"I4LWH","isRack":false,"critRules":false}],"weapons":[{"name":"pds","id":"l5LdK"},{"name":"pds","id":"vwGAa"},{"name":"pds","id":"gh3ru"},{"name":"pds","id":"aDMFK"},{"name":"pds","id":"IpY96"},{"name":"pds","id":"25H7F"},{"name":"beam","class":1,"leftArc":"F","numArcs":6,"id":"BepZp"},{"name":"beam","class":1,"leftArc":"F","numArcs":6,"id":"Ds8zO"},{"name":"beam","class":2,"leftArc":"AP","numArcs":3,"id":"Vj_AN"},{"name":"beam","class":2,"leftArc":"AP","numArcs":3,"id":"ERb4o"},{"name":"beam","class":2,"leftArc":"F","numArcs":3,"id":"Ve2aC"},{"name":"beam","class":2,"leftArc":"F","numArcs":3,"id":"C6rZc"},{"name":"beam","class":3,"leftArc":"AP","numArcs":3,"id":"r34r8"},{"name":"beam","class":3,"leftArc":"FP","numArcs":3,"id":"1mABJ"},{"name":"beam","class":3,"leftArc":"FP","numArcs":3,"id":"xjptS"},{"name":"beam","class":3,"leftArc":"F","numArcs":3,"id":"7fLe0"}],"ordnance":[],"extras":[],"fighters":[{"name":"fighters","type":"standard","id":"lgrLB","mods":[],"hangar":"EQ2W6"},{"name":"fighters","type":"standard","id":"4xXE-","mods":[],"hangar":"sw_ET"},{"name":"fighters","type":"standard","id":"viaG3","mods":[],"hangar":"DRonE"},{"name":"fighters","type":"standard","id":"pdLwG","mods":[],"hangar":"5hxLH"},{"name":"fighters","type":"standard","id":"brJEp","mods":[],"hangar":"FJl7X"},{"name":"fighters","type":"standard","id":"ykKy1","mods":[],"hangar":"I4LWH"}],"orientation":"alpha","points":842,"cpv":840,"mass":240,"class":"Attack Carrier","name":"Konstantin"}
        ]
    },
    {
        "name": "Merchant & Support Vessels",
        "ships": [
            {"hull":{"points":12,"rows":4,"stealth":"0","streamlining":"none"},"armour":[],"systems":[{"name":"drive","thrust":2,"advanced":false,"id":"DpPj8"},{"name":"ftl","advanced":false,"id":"WfKq9"},{"name":"bay","id":"h7KwX","capacity":21,"type":"cargo"},{"name":"bay","id":"V196j","capacity":21,"type":"cargo"},{"name":"bay","id":"SLb6M","capacity":21,"type":"cargo"},{"name":"bay","id":"rB2xm","capacity":20,"type":"cargo"}],"weapons":[{"name":"pds","id":"agfdD"}],"ordnance":[],"extras":[],"fighters":[],"orientation":"alpha","points":195,"cpv":89,"mass":120,"class":"Civilian","name":"Heavy Freighter","civilian":true},
            {"hull":{"points":8,"rows":4,"stealth":"0","streamlining":"none"},"armour":[],"systems":[{"name":"drive","thrust":2,"advanced":false,"id":"QKCM6"},{"name":"ftl","advanced":false,"id":"KhFzo"},{"name":"bay","id":"Z9FCQ","capacity":14,"type":"cargo"},{"name":"bay","id":"f3IJX","capacity":14,"type":"cargo"},{"name":"bay","id":"0Ne4O","capacity":14,"type":"cargo"},{"name":"bay","id":"_7rGd","capacity":13,"type":"cargo"}],"weapons":[{"name":"pds","id":"qoKgr"}],"ordnance":[],"extras":[],"fighters":[],"orientation":"alpha","points":131,"cpv":57,"mass":80,"class":"Civilian","name":"Medium Freighter","civilian":true},
            {"hull":{"points":4,"rows":4,"stealth":"0","streamlining":"none"},"armour":[],"systems":[{"name":"drive","thrust":2,"advanced":false,"id":"X2EtC"},{"name":"ftl","advanced":false,"id":"4QATK"},{"name":"bay","id":"pstid","capacity":7,"type":"cargo"},{"name":"bay","id":"DLWtx","capacity":7,"type":"cargo"},{"name":"bay","id":"r1-cP","capacity":7,"type":"cargo"},{"name":"bay","id":"m3L6n","capacity":6,"type":"cargo"}],"weapons":[{"name":"pds","id":"10yfT"}],"ordnance":[],"extras":[],"fighters":[],"orientation":"alpha","points":67,"cpv":29,"mass":40,"class":"Civilian","name":"Light Freighter","civilian":true},
            {"hull":{"points":4,"rows":4,"stealth":"0","streamlining":"none"},"armour":[],"systems":[{"name":"drive","thrust":4,"advanced":false,"id":"IQKjC"},{"name":"ftl","advanced":false,"id":"JaGD6"},{"name":"bay","id":"qV0p8","capacity":2,"type":"cargo"},{"name":"bay","id":"A7s2I","capacity":2,"type":"cargo"},{"name":"bay","id":"UJSYx","capacity":2,"type":"cargo"},{"name":"bay","id":"m8bvE","capacity":2,"type":"cargo"},{"name":"fireControl","id":"jMrUq"}],"weapons":[{"name":"beam","class":1,"leftArc":"F","numArcs":6,"id":"kq7MZ"}],"ordnance":[],"extras":[],"fighters":[],"orientation":"alpha","points":47,"cpv":28,"mass":20,"class":"Civilian","name":"Free Trader","civilian":true},
            {"hull":{"points":20,"rows":4,"stealth":"0","streamlining":"none"},"armour":[],"systems":[{"name":"drive","thrust":2,"advanced":false,"id":"baTvv"},{"name":"ftl","advanced":false,"id":"F9zZZ"},{"name":"fireControl","id":"venOJ"},{"name":"bay","id":"ytJiG","capacity":14,"type":"cargo"},{"name":"bay","id":"UAG_a","capacity":14,"type":"cargo"},{"name":"bay","id":"piyjk","capacity":14,"type":"cargo"},{"name":"bay","id":"3KqjS","capacity":14,"type":"cargo"}],"weapons":[{"name":"pds","id":"uUyQL"},{"name":"pds","id":"nST0l"},{"name":"beam","class":1,"leftArc":"F","numArcs":6,"id":"j7Fgp"}],"ordnance":[],"extras":[],"fighters":[],"orientation":"alpha","points":193,"cpv":112,"mass":100,"class":"Civilian","name":"Fleet Auxiliary","civilian":true},
            {"hull":{"points":20,"rows":4,"stealth":"0","streamlining":"none"},"armour":[],"systems":[{"name":"drive","thrust":1,"advanced":false,"id":"DBn5b"},{"name":"ftl","advanced":false,"id":"NyYdV"},{"name":"bay","id":"BX_K9","capacity":38,"type":"cargo"},{"name":"bay","id":"_QXFo","capacity":37,"type":"cargo"},{"name":"bay","id":"1Eooq","capacity":37,"type":"cargo"},{"name":"bay","id":"AuIvU","capacity":37,"type":"cargo"}],"weapons":[{"name":"pds","id":"iQndC"}],"ordnance":[],"extras":[],"fighters":[],"orientation":"alpha","points":303,"cpv":129,"mass":200,"class":"Civilian","name":"Bulk Carrier","civilian":true},
            {"hull":{"points":12,"rows":4,"stealth":"0","streamlining":"none"},"armour":[],"systems":[{"name":"drive","thrust":2,"advanced":false,"id":"1o8TS"},{"name":"ftl","advanced":false,"id":"JJda2"},{"name":"fireControl","id":"lKUi9"},{"name":"bay","id":"j3HW8","capacity":80,"type":"passenger"},{"name":"bay","id":"kbiHH","capacity":80,"type":"passenger"},{"name":"bay","id":"_nTtK","capacity":80,"type":"passenger"},{"name":"bay","id":"oUoBr","capacity":80,"type":"passenger"}],"weapons":[{"name":"pds","id":"Ihx9E"},{"name":"pds","id":"ATq0M"},{"name":"beam","class":1,"leftArc":"F","numArcs":6,"id":"TssQD"}],"ordnance":[],"extras":[],"fighters":[],"orientation":"alpha","points":205,"cpv":101,"mass":120,"class":"Civilian","name":"Starliner","civilian":true}
        ]
    },
    {
        "name": "Kra'Vak",
        "ships": [
            {"hull":{"points":3,"rows":4,"stealth":"0","streamlining":"none"},"armour":[],"systems":[{"name":"drive","thrust":6,"advanced":true,"id":"eEIDI"},{"name":"ftl","advanced":false,"id":"EZkRs"},{"name":"fireControl","id":"elXoM"}],"weapons":[{"name":"kgun","class":1,"leftArc":"F","numArcs":6,"id":"Fh3-H"},{"name":"mkp","arc":"F","id":"77tit"}],"ordnance":[],"extras":[],"fighters":[],"orientation":"alpha","points":44,"cpv":34,"mass":11,"class":"Sneak Deadly Killer","name":"Lu'Dak"},
            {"hull":{"points":6,"rows":4,"stealth":"0","streamlining":"none"},"armour":[],"systems":[{"name":"drive","thrust":6,"advanced":true,"id":"V3W1L"},{"name":"ftl","advanced":false,"id":"9t0su"},{"name":"fireControl","id":"GUOv8"}],"weapons":[{"name":"kgun","class":1,"leftArc":"F","numArcs":6,"id":"XUdx2"},{"name":"mkp","arc":"F","id":"7dRMR"},{"name":"mkp","arc":"F","id":"LeXG0"},{"name":"scatterGun","id":"EfB8j"}],"ordnance":[],"extras":[],"fighters":[],"orientation":"alpha","points":79,"cpv":63,"mass":20,"class":"Raider Dark Killer","name":"Ka'Tak"},
            {"hull":{"points":9,"rows":4,"stealth":"0","streamlining":"none"},"armour":[],"systems":[{"name":"drive","thrust":6,"advanced":true,"id":"wuObM"},{"name":"ftl","advanced":false,"id":"U37SJ"},{"name":"fireControl","id":"IbY3R"}],"weapons":[{"name":"kgun","class":2,"leftArc":"F","numArcs":1,"id":"ioPPV"},{"name":"kgun","class":2,"leftArc":"F","numArcs":1,"id":"oA0dj"},{"name":"scatterGun","id":"OuZGw"},{"name":"scatterGun","id":"_O5_z"}],"ordnance":[],"extras":[],"fighters":[],"orientation":"alpha","points":119,"cpv":98,"mass":30,"class":"Swift War Killer","name":"Da'Kak"},
            {"hull":{"points":12,"rows":4,"stealth":"0","streamlining":"none"},"armour":[],"systems":[{"name":"drive","thrust":6,"advanced":true,"id":"16vks"},{"name":"ftl","advanced":false,"id":"l9WtA"},{"name":"fireControl","id":"ofPNT"}],"weapons":[{"name":"scatterGun","id":"M1QeV"},{"name":"scatterGun","id":"oqFB9"},{"name":"scatterGun","id":"bb_R_"},{"name":"kgun","class":1,"leftArc":"F","numArcs":6,"id":"vfwSM"},{"name":"kgun","class":2,"leftArc":"F","numArcs":1,"id":"R5qiK"},{"name":"kgun","class":2,"leftArc":"F","numArcs":1,"id":"7S5g6"}],"ordnance":[],"extras":[],"fighters":[],"orientation":"alpha","points":159,"cpv":135,"mass":40,"class":"Little Death Dark Ship","name":"Di'Tok"},
            {"hull":{"points":18,"rows":4,"stealth":"0","streamlining":"none"},"armour":[],"systems":[{"name":"drive","thrust":6,"advanced":true,"id":"bY8uw"},{"name":"ftl","advanced":false,"id":"0chbT"},{"name":"fireControl","id":"Kzx4v"},{"name":"fireControl","id":"tTd3_"}],"weapons":[{"name":"kgun","class":1,"leftArc":"F","numArcs":6,"id":"5qvT2"},{"name":"kgun","class":3,"leftArc":"F","numArcs":1,"id":"ZhjO1"},{"name":"kgun","class":3,"leftArc":"F","numArcs":1,"id":"kKXby"},{"name":"scatterGun","id":"k9pCs"},{"name":"scatterGun","id":"RB9yG"},{"name":"scatterGun","id":"t8vPy"},{"name":"scatterGun","id":"hIPGL"}],"ordnance":[],"extras":[],"fighters":[],"orientation":"alpha","points":238,"cpv":214,"mass":60,"class":"Hunter Silent Ship","name":"Vo'Bok"},
            {"hull":{"points":21,"rows":4,"stealth":"0","streamlining":"none"},"armour":[],"systems":[{"name":"drive","thrust":6,"advanced":true,"id":"EAnEQ"},{"name":"ftl","advanced":false,"id":"ehnhg"},{"name":"fireControl","id":"5U6KV"},{"name":"fireControl","id":"vKZ49"}],"weapons":[{"name":"kgun","class":1,"leftArc":"F","numArcs":6,"id":"812iU"},{"name":"kgun","class":1,"leftArc":"F","numArcs":6,"id":"WdOg7"},{"name":"kgun","class":3,"leftArc":"F","numArcs":1,"id":"YWr_Y"},{"name":"kgun","class":3,"leftArc":"F","numArcs":1,"id":"n2Z_f"},{"name":"scatterGun","id":"zCUHb"},{"name":"scatterGun","id":"slwIS"},{"name":"scatterGun","id":"6l9F2"},{"name":"scatterGun","id":"u3Nao"},{"name":"scatterGun","id":"Lzv91"}],"ordnance":[],"extras":[],"fighters":[],"orientation":"alpha","points":278,"cpv":257,"mass":70,"class":"Rover Dark Ship","name":"Si'Tek"},
            {"hull":{"points":21,"rows":4,"stealth":"0","streamlining":"none"},"armour":[],"systems":[{"name":"drive","thrust":6,"advanced":true,"id":"Sarvn"},{"name":"ftl","advanced":false,"id":"9-B9z"},{"name":"fireControl","id":"mNBI5"},{"name":"fireControl","id":"3k0Xu"}],"weapons":[{"name":"kgun","class":1,"leftArc":"F","numArcs":6,"id":"39O17"},{"name":"kgun","class":3,"leftArc":"F","numArcs":1,"id":"MbJSN"},{"name":"kgun","class":3,"leftArc":"F","numArcs":1,"id":"9UyzW"},{"name":"kgun","class":3,"leftArc":"F","numArcs":1,"id":"2gvqE"},{"name":"scatterGun","id":"YkXNC"},{"name":"scatterGun","id":"nXLoM"}],"ordnance":[],"extras":[],"fighters":[],"orientation":"alpha","points":275,"cpv":254,"mass":70,"class":"Attack Dark Ship","name":"Ko'Tek"},
            {"hull":{"points":27,"rows":4,"stealth":"0","streamlining":"none"},"armour":[],"systems":[{"name":"drive","thrust":6,"advanced":true,"id":"FJoT4"},{"name":"ftl","advanced":false,"id":"1ItxX"},{"name":"fireControl","id":"xDSR_"},{"name":"fireControl","id":"psiPv"}],"weapons":[{"name":"kgun","class":1,"leftArc":"F","numArcs":6,"id":"qXo_K"},{"name":"kgun","class":4,"leftArc":"F","numArcs":1,"id":"lW7jA"},{"name":"kgun","class":4,"leftArc":"F","numArcs":1,"id":"VQe-S"},{"name":"scatterGun","id":"n5wX9"},{"name":"scatterGun","id":"la1N9"},{"name":"scatterGun","id":"JCCrW"},{"name":"scatterGun","id":"j1wcr"}],"ordnance":[],"extras":[],"fighters":[],"orientation":"alpha","points":329,"cpv":316,"mass":84,"class":"Great Deadly Ship","name":"Va'Dok"},
            {"hull":{"points":36,"rows":4,"stealth":"0","streamlining":"none"},"armour":[],"systems":[{"name":"drive","thrust":4,"advanced":true,"id":"nd093"},{"name":"ftl","advanced":false,"id":"p64k0"},{"name":"fireControl","id":"ycT9X"},{"name":"fireControl","id":"gSFBm"},{"name":"fireControl","id":"4Uvxu"}],"weapons":[{"name":"kgun","class":1,"leftArc":"F","numArcs":6,"id":"woUEI"},{"name":"kgun","class":1,"leftArc":"F","numArcs":6,"id":"JjZvk"},{"name":"kgun","class":5,"leftArc":"F","numArcs":1,"id":"h2emW"},{"name":"kgun","class":5,"leftArc":"F","numArcs":1,"id":"uFI-H"},{"name":"scatterGun","id":"Tr4aV"},{"name":"scatterGun","id":"ghLRI"},{"name":"scatterGun","id":"44DXn"},{"name":"scatterGun","id":"xMbFJ"},{"name":"scatterGun","id":"27Le6"}],"ordnance":[],"extras":[],"fighters":[],"orientation":"alpha","points":393,"cpv":393,"mass":100,"class":"Fight Deadly Flyer","name":"Ti'Dak"},
            {"hull":{"points":48,"rows":4,"stealth":"0","streamlining":"none"},"armour":[],"systems":[{"name":"drive","thrust":4,"advanced":true,"id":"tJfZg"},{"name":"ftl","advanced":false,"id":"Qykci"},{"name":"fireControl","id":"XhFow"},{"name":"fireControl","id":"VBSoY"},{"name":"fireControl","id":"uZVwh"}],"weapons":[{"name":"kgun","class":1,"leftArc":"F","numArcs":6,"id":"AFKAD"},{"name":"kgun","class":1,"leftArc":"F","numArcs":6,"id":"OErGv"},{"name":"kgun","class":1,"leftArc":"F","numArcs":6,"id":"1m65D"},{"name":"kgun","class":5,"leftArc":"F","numArcs":1,"id":"xPJAs"},{"name":"kgun","class":5,"leftArc":"F","numArcs":1,"id":"Balgw"},{"name":"scatterGun","id":"xPNru"},{"name":"scatterGun","id":"MRiW1"},{"name":"scatterGun","id":"2hXEC"},{"name":"scatterGun","id":"8jrLc"},{"name":"scatterGun","id":"Ylr7i"},{"name":"scatterGun","id":"M27dv"}],"ordnance":[],"extras":[],"fighters":[],"orientation":"alpha","points":467,"cpv":492,"mass":121,"class":"Attack Sorrow Monster","name":"Ko'Vol"},
            {"hull":{"points":54,"rows":4,"stealth":"0","streamlining":"none"},"armour":[],"systems":[{"name":"drive","thrust":4,"advanced":true,"id":"q_QxF"},{"name":"ftl","advanced":false,"id":"bOTs5"},{"name":"fireControl","id":"ZX6D7"},{"name":"fireControl","id":"hYrQ_"},{"name":"fireControl","id":"oY9Cl"},{"name":"fireControl","id":"A7qq0"},{"name":"hangar","id":"5ngOD","isRack":false,"critRules":false}],"weapons":[{"name":"kgun","class":1,"leftArc":"F","numArcs":6,"id":"TrFul"},{"name":"kgun","class":1,"leftArc":"F","numArcs":6,"id":"VEPUh"},{"name":"kgun","class":1,"leftArc":"F","numArcs":6,"id":"I3haG"},{"name":"kgun","class":3,"leftArc":"F","numArcs":1,"id":"MX7gb"},{"name":"kgun","class":3,"leftArc":"F","numArcs":1,"id":"2iLOH"},{"name":"kgun","class":5,"leftArc":"F","numArcs":1,"id":"XfPHI"},{"name":"kgun","class":5,"leftArc":"F","numArcs":1,"id":"DOcL0"},{"name":"scatterGun","id":"UMfMJ"},{"name":"scatterGun","id":"LKB2t"},{"name":"scatterGun","id":"N6ALU"},{"name":"scatterGun","id":"OJgsX"},{"name":"scatterGun","id":"lwWyZ"},{"name":"scatterGun","id":"CzW5f"},{"name":"scatterGun","id":"2WU1x"}],"ordnance":[],"extras":[],"fighters":[{"name":"fighters","type":"standard","id":"c-j3V","mods":[],"hangar":"5ngOD"}],"orientation":"alpha","points":626,"cpv":676,"mass":160,"class":"Great Death Sorrow Ship","name":"Lo'Vok"},
            {"hull":{"points":72,"rows":4,"stealth":"0","streamlining":"none"},"armour":[],"systems":[{"name":"drive","thrust":3,"advanced":true,"id":"fFiA2"},{"name":"ftl","advanced":false,"id":"g1pAo"},{"name":"fireControl","id":"r6WVC"},{"name":"fireControl","id":"Fii_q"},{"name":"fireControl","id":"TFv4W"},{"name":"fireControl","id":"khFnR"},{"name":"fireControl","id":"LegD-"},{"name":"hangar","id":"JhdF4","isRack":false,"critRules":false}],"weapons":[{"name":"kgun","class":1,"leftArc":"F","numArcs":6,"id":"qfxki"},{"name":"kgun","class":1,"leftArc":"F","numArcs":6,"id":"s0q6p"},{"name":"kgun","class":1,"leftArc":"F","numArcs":6,"id":"trEiu"},{"name":"kgun","class":1,"leftArc":"F","numArcs":6,"id":"YCbgR"},{"name":"kgun","class":1,"leftArc":"F","numArcs":6,"id":"DHlAd"},{"name":"kgun","class":6,"leftArc":"F","numArcs":1,"id":"3tkEv"},{"name":"kgun","class":6,"leftArc":"F","numArcs":1,"id":"eFV6C"},{"name":"kgun","class":6,"leftArc":"F","numArcs":1,"id":"hCCU2"},{"name":"kgun","class":6,"leftArc":"F","numArcs":1,"id":"DpGQV"},{"name":"scatterGun","id":"dnH4S"},{"name":"scatterGun","id":"DsmXo"},{"name":"scatterGun","id":"w4atG"},{"name":"scatterGun","id":"Myavs"},{"name":"scatterGun","id":"LRTN6"},{"name":"scatterGun","id":"wG6CB"},{"name":"scatterGun","id":"EOq1f"},{"name":"scatterGun","id":"1LwHR"},{"name":"scatterGun","id":"aVqZN"},{"name":"scatterGun","id":"i5q9_"},{"name":"scatterGun","id":"7e6pt"},{"name":"scatterGun","id":"e0NPD"},{"name":"scatterGun","id":"aBrY1"}],"ordnance":[],"extras":[],"fighters":[{"name":"fighters","type":"standard","id":"BCee7","mods":[],"hangar":"JhdF4"}],"orientation":"alpha","points":883,"cpv":1090,"mass":220,"class":"Ruler War Mountain","name":"Yu'Kas"},
            {"hull":{"points":54,"rows":4,"stealth":"0","streamlining":"none"},"armour":[],"systems":[{"name":"drive","thrust":4,"advanced":true,"id":"oKLzo"},{"name":"ftl","advanced":false,"id":"0Vquk"},{"name":"fireControl","id":"FW1P_"},{"name":"fireControl","id":"7DwoO"},{"name":"fireControl","id":"Mgwse"},{"name":"hangar","id":"fxZqd","isRack":false,"critRules":false},{"name":"hangar","id":"UxjnL","isRack":false,"critRules":false},{"name":"hangar","id":"H8J_s","isRack":false,"critRules":false},{"name":"hangar","id":"DvYwT","isRack":false,"critRules":false}],"weapons":[{"name":"kgun","class":1,"leftArc":"F","numArcs":6,"id":"03GQo"},{"name":"kgun","class":1,"leftArc":"F","numArcs":6,"id":"Us2oB"},{"name":"kgun","class":1,"leftArc":"F","numArcs":6,"id":"QS8GR"},{"name":"kgun","class":3,"leftArc":"F","numArcs":1,"id":"-btQI"},{"name":"kgun","class":3,"leftArc":"F","numArcs":1,"id":"z3pQu"},{"name":"kgun","class":3,"leftArc":"F","numArcs":1,"id":"kuHBl"},{"name":"kgun","class":3,"leftArc":"F","numArcs":1,"id":"0xq9P"},{"name":"scatterGun","id":"IEhrf"},{"name":"scatterGun","id":"PyzhI"},{"name":"scatterGun","id":"5zaOm"},{"name":"scatterGun","id":"1Kn2K"},{"name":"scatterGun","id":"Uhqcf"},{"name":"scatterGun","id":"Ig3Nz"},{"name":"scatterGun","id":"fyAOW"}],"ordnance":[],"extras":[],"fighters":[{"name":"fighters","type":"standard","id":"bRdic","mods":[],"hangar":"fxZqd"},{"name":"fighters","type":"standard","id":"p2lIa","mods":[],"hangar":"UxjnL"},{"name":"fighters","type":"standard","id":"odXmd","mods":[],"hangar":"H8J_s"},{"name":"fighters","type":"standard","id":"7_YE2","mods":[],"hangar":"DvYwT"}],"orientation":"alpha","points":691,"cpv":646,"mass":180,"class":"Follower Sliver Mother","name":"Do'San"},
            {"hull":{"points":72,"rows":4,"stealth":"0","streamlining":"none"},"armour":[],"systems":[{"name":"drive","thrust":4,"advanced":true,"id":"R9pS8"},{"name":"ftl","advanced":false,"id":"vAaf8"},{"name":"fireControl","id":"jrNHJ"},{"name":"fireControl","id":"s3Z9U"},{"name":"fireControl","id":"3l0sk"},{"name":"hangar","id":"VaiC_","isRack":false,"critRules":false},{"name":"hangar","id":"kx6Gg","isRack":false,"critRules":false},{"name":"hangar","id":"sUQwh","isRack":false,"critRules":false},{"name":"hangar","id":"ppKff","isRack":false,"critRules":false},{"name":"hangar","id":"AmzAp","isRack":false,"critRules":false},{"name":"hangar","id":"hUp5h","isRack":false,"critRules":false}],"weapons":[{"name":"kgun","class":1,"leftArc":"F","numArcs":6,"id":"v3Q46"},{"name":"kgun","class":1,"leftArc":"F","numArcs":6,"id":"lvOJV"},{"name":"kgun","class":1,"leftArc":"F","numArcs":6,"id":"ftm_9"},{"name":"kgun","class":1,"leftArc":"F","numArcs":6,"id":"iAQJ4"},{"name":"kgun","class":3,"leftArc":"F","numArcs":1,"id":"4Ersi"},{"name":"kgun","class":3,"leftArc":"F","numArcs":1,"id":"mQ_lm"},{"name":"kgun","class":3,"leftArc":"F","numArcs":1,"id":"OqBwf"},{"name":"kgun","class":3,"leftArc":"F","numArcs":1,"id":"IFJYc"},{"name":"scatterGun","id":"Edigb"},{"name":"scatterGun","id":"Wdr9b"},{"name":"scatterGun","id":"THMMD"},{"name":"scatterGun","id":"8ZFiz"},{"name":"scatterGun","id":"idyjT"},{"name":"scatterGun","id":"5Y8qB"},{"name":"scatterGun","id":"ve_lm"},{"name":"scatterGun","id":"YsdFc"},{"name":"scatterGun","id":"oRjs_"},{"name":"scatterGun","id":"W75A8"},{"name":"scatterGun","id":"iMYjk"}],"ordnance":[],"extras":[],"fighters":[{"name":"fighters","type":"standard","id":"PXubY","mods":[],"hangar":"VaiC_"},{"name":"fighters","type":"standard","id":"F2RDi","mods":[],"hangar":"kx6Gg"},{"name":"fighters","type":"standard","id":"sRP2f","mods":[],"hangar":"sUQwh"},{"name":"fighters","type":"standard","id":"Ndq7Y","mods":[],"hangar":"ppKff"},{"name":"fighters","type":"standard","id":"_scqq","mods":[],"hangar":"AmzAp"},{"name":"fighters","type":"standard","id":"ddxHv","mods":[],"hangar":"hUp5h"}],"orientation":"alpha","points":917,"cpv":915,"mass":240,"class":"Attack Sliver Mother","name":"Ko'San"},
            {"hull":{"points":10,"rows":4,"stealth":"0","streamlining":"none"},"armour":[],"systems":[{"name":"drive","thrust":2,"advanced":true,"id":"f_OD0"},{"name":"ftl","advanced":false,"id":"JyQaC"},{"name":"fireControl","id":"i1JQA"},{"name":"bay","id":"wj_Lt","capacity":5,"type":"cargo"},{"name":"bay","id":"NmGkh","capacity":5,"type":"cargo"},{"name":"bay","id":"ds1YD","capacity":4,"type":"cargo"},{"name":"bay","id":"I-_R1","capacity":4,"type":"cargo"}],"weapons":[{"name":"kgun","class":1,"leftArc":"F","numArcs":6,"id":"lBVae"},{"name":"scatterGun","id":"e-xE1"}],"ordnance":[],"extras":[],"fighters":[],"orientation":"alpha","points":97,"cpv":62,"mass":40,"class":"War Supplies Mover","name":"Sha'Ken","civilian":true},
            {"hull":{"points":18,"rows":4,"stealth":"0","streamlining":"none"},"armour":[],"systems":[{"name":"drive","thrust":4,"advanced":true,"id":"-XSOU"},{"name":"ftl","advanced":false,"id":"ct2js"},{"name":"fireControl","id":"d77W_"},{"name":"bay","id":"um42S","capacity":3,"type":"cargo"},{"name":"bay","id":"W2W43","capacity":3,"type":"cargo"},{"name":"bay","id":"81HsG","capacity":2,"type":"cargo"},{"name":"bay","id":"-B6DN","capacity":2,"type":"cargo"},{"name":"bay","id":"u3x_K","capacity":4,"type":"boat"}],"weapons":[{"name":"kgun","class":1,"leftArc":"F","numArcs":6,"id":"4Ujiw"},{"name":"kgun","class":2,"leftArc":"F","numArcs":1,"id":"FvhLD"},{"name":"scatterGun","id":"q9Vsb"},{"name":"scatterGun","id":"U-0Ae"}],"ordnance":[],"extras":[],"fighters":[],"orientation":"alpha","points":178,"cpv":137,"mass":60,"class":"Seeker Stealthy Ship","name":"To'Rok","civilian":false}
        ]
    },
    {
        "name": "Phalon",
        "ships": [
            {"hull":{"points":3,"rows":4,"stealth":"0","streamlining":"none"},"armour":[[2,0]],"systems":[{"name":"drive","thrust":6,"advanced":false,"id":"F-wFJ"},{"name":"ftl","advanced":false,"id":"WGZuu"},{"name":"shroud","id":"Mjy9e"},{"name":"fireControl","id":"DLsVc"}],"weapons":[{"name":"pulser","leftArc":"FP","numArcs":3,"id":"Dp0uj"},{"name":"pbl","class":1,"leftArc":"FP","numArcs":3,"id":"jlztV"}],"ordnance":[],"extras":[],"fighters":[],"orientation":"alpha","points":89,"cpv":71,"mass":24,"class":"Protector","name":"Phuun"},
            {"hull":{"points":7,"rows":4,"stealth":"0","streamlining":"none"},"armour":[[4,0]],"systems":[{"name":"drive","thrust":6,"advanced":false,"id":"v52rj"},{"name":"ftl","advanced":false,"id":"LQBxt"},{"name":"fireControl","id":"X5LQy"},{"name":"shroud","id":"mvDIZ"}],"weapons":[{"name":"pulser","leftArc":"F","numArcs":6,"id":"7SqwG"},{"name":"pulser","leftArc":"F","numArcs":1,"id":"X6Pdo"},{"name":"pbl","class":1,"leftArc":"FP","numArcs":3,"id":"lB8_t"}],"ordnance":[],"extras":[],"fighters":[],"orientation":"alpha","points":150,"cpv":126,"mass":41,"class":"Protector","name":"Dinth"},
            {"hull":{"points":10,"rows":4,"stealth":"0","streamlining":"none"},"armour":[[3,0],[2,0]],"systems":[{"name":"drive","thrust":4,"advanced":false,"id":"yEWd7"},{"name":"ftl","advanced":false,"id":"UP7fb"},{"name":"fireControl","id":"NH_Eb"},{"name":"fireControl","id":"-IaAr"},{"name":"shroud","id":"zqJ8u"}],"weapons":[{"name":"pulser","leftArc":"F","numArcs":6,"id":"8gSUq"},{"name":"pulser","leftArc":"F","numArcs":6,"id":"kFfNR"},{"name":"pulser","leftArc":"F","numArcs":1,"id":"wLSRn"},{"name":"pbl","class":2,"leftArc":"FP","numArcs":3,"id":"fgOl5"}],"ordnance":[],"extras":[],"fighters":[],"orientation":"alpha","points":225,"cpv":201,"mass":58,"class":"Warrior","name":"Tsaara"},
            {"hull":{"points":12,"rows":4,"stealth":"0","streamlining":"none"},"armour":[[4,0],[3,0]],"systems":[{"name":"drive","thrust":4,"advanced":false,"id":"5zf_p"},{"name":"ftl","advanced":false,"id":"6wYWi"},{"name":"fireControl","id":"TGN9r"},{"name":"fireControl","id":"HBfYS"},{"name":"shroud","id":"xFOJ9"}],"weapons":[{"name":"pulser","leftArc":"F","numArcs":6,"id":"xzaig"},{"name":"pulser","leftArc":"F","numArcs":6,"id":"Li8wD"},{"name":"pulser","leftArc":"AP","numArcs":3,"id":"EoI-V"},{"name":"pulser","leftArc":"F","numArcs":3,"id":"evL5W"},{"name":"pbl","class":2,"leftArc":"FP","numArcs":3,"id":"oeZiG"}],"ordnance":[],"extras":[],"fighters":[],"orientation":"alpha","points":276,"cpv":255,"mass":70,"class":"Warrior","name":"Huulth"},
            {"hull":{"points":16,"rows":4,"stealth":"0","streamlining":"none"},"armour":[[6,0],[3,0]],"systems":[{"name":"drive","thrust":4,"advanced":false,"id":"FF6by"},{"name":"ftl","advanced":false,"id":"8HJrd"},{"name":"fireControl","id":"SRS_i"},{"name":"fireControl","id":"ZYwTo"},{"name":"shroud","id":"XvSZz"}],"weapons":[{"name":"pulser","leftArc":"F","numArcs":6,"id":"VAJ-4"},{"name":"pulser","leftArc":"AP","numArcs":3,"id":"GzR_z"},{"name":"pulser","leftArc":"F","numArcs":3,"id":"D8ugZ"},{"name":"pbl","class":3,"leftArc":"FP","numArcs":3,"id":"rWVfw"}],"ordnance":[],"extras":[],"fighters":[],"orientation":"alpha","points":299,"cpv":283,"mass":80,"class":"Warrior","name":"Tuuloth"},
            {"hull":{"points":20,"rows":4,"stealth":"0","streamlining":"none"},"armour":[[8,0],[4,0]],"systems":[{"name":"drive","thrust":4,"advanced":false,"id":"s4dy9"},{"name":"ftl","advanced":false,"id":"HojMe"},{"name":"adfc","id":"8--9y"},{"name":"fireControl","id":"9oLTD"},{"name":"fireControl","id":"AyFjQ"},{"name":"fireControl","id":"YBX4v"},{"name":"shroud","id":"-6ZQ-"}],"weapons":[{"name":"pulser","leftArc":"F","numArcs":6,"id":"0FJXf"},{"name":"pulser","leftArc":"F","numArcs":6,"id":"9O0wt"},{"name":"pulser","leftArc":"F","numArcs":1,"id":"VlyI6"},{"name":"pulser","leftArc":"AP","numArcs":3,"id":"VFBDo"},{"name":"pulser","leftArc":"F","numArcs":3,"id":"l0Rgo"},{"name":"pbl","class":3,"leftArc":"FP","numArcs":3,"id":"Zihaa"}],"ordnance":[],"extras":[],"fighters":[],"orientation":"alpha","points":398,"cpv":402,"mass":104,"class":"Warrior","name":"Keraph"},
            {"hull":{"points":24,"rows":4,"stealth":"0","streamlining":"none"},"armour":[[8,0],[4,0],[4,0]],"systems":[{"name":"drive","thrust":4,"advanced":false,"id":"fpjAn"},{"name":"ftl","advanced":false,"id":"4b3Q3"},{"name":"fireControl","id":"tACNh"},{"name":"fireControl","id":"WuJ-y"},{"name":"fireControl","id":"_nFWy"},{"name":"shroud","id":"L4LA5"}],"weapons":[{"name":"pulser","leftArc":"F","numArcs":6,"id":"Rio6E"},{"name":"pulser","leftArc":"F","numArcs":6,"id":"2FgWB"},{"name":"pulser","leftArc":"AP","numArcs":3,"id":"C4xw1"},{"name":"pulser","leftArc":"FP","numArcs":3,"id":"c2BDZ"},{"name":"pulser","leftArc":"FP","numArcs":3,"id":"QsJWD"},{"name":"pulser","leftArc":"FP","numArcs":3,"id":"YvCKH"},{"name":"pulser","leftArc":"F","numArcs":3,"id":"9Yauk"},{"name":"pbl","class":4,"leftArc":"FP","numArcs":3,"id":"NVoXv"}],"ordnance":[],"extras":[],"fighters":[],"orientation":"alpha","points":522,"cpv":564,"mass":132,"class":"Great Warrior","name":"Ptath"},
            {"hull":{"points":30,"rows":4,"stealth":"0","streamlining":"none"},"armour":[[9,0],[5,0],[4,0]],"systems":[{"name":"drive","thrust":4,"advanced":false,"id":"KVfM9"},{"name":"ftl","advanced":false,"id":"ehl68"},{"name":"fireControl","id":"JgHAe"},{"name":"fireControl","id":"Q34me"},{"name":"fireControl","id":"GctKx"},{"name":"shroud","id":"Z5uxr"}],"weapons":[{"name":"pulser","leftArc":"F","numArcs":6,"id":"B5oZs"},{"name":"pulser","leftArc":"F","numArcs":6,"id":"cfsqa"},{"name":"pulser","leftArc":"F","numArcs":6,"id":"b1Q6U"},{"name":"pulser","leftArc":"AP","numArcs":3,"id":"5FzmG"},{"name":"pulser","leftArc":"FP","numArcs":3,"id":"EyYym"},{"name":"pulser","leftArc":"FP","numArcs":3,"id":"VPAsg"},{"name":"pulser","leftArc":"F","numArcs":3,"id":"-pmdS"},{"name":"pbl","class":2,"leftArc":"FP","numArcs":3,"id":"d8mAY"},{"name":"pbl","class":5,"leftArc":"FP","numArcs":3,"id":"ZsI6s"}],"ordnance":[],"extras":[],"fighters":[],"orientation":"alpha","points":658,"cpv":777,"mass":170,"class":"Great Warrior","name":"Saath"},
            {"hull":{"points":42,"rows":4,"stealth":"0","streamlining":"none"},"armour":[[16,0],[10,0],[8,0],[6,0]],"systems":[{"name":"drive","thrust":2,"advanced":false,"id":"As4ka"},{"name":"ftl","advanced":false,"id":"fTxwk"},{"name":"fireControl","id":"7_m7c"},{"name":"fireControl","id":"-1dPT"},{"name":"fireControl","id":"VaMD_"},{"name":"fireControl","id":"b7sZw"},{"name":"fireControl","id":"FF-5O"},{"name":"shroud","id":"qwFtv"}],"weapons":[{"name":"pulser","leftArc":"F","numArcs":6,"id":"JBnVw"},{"name":"pulser","leftArc":"F","numArcs":6,"id":"a9iVO"},{"name":"pulser","leftArc":"F","numArcs":6,"id":"CvxbT"},{"name":"pulser","leftArc":"F","numArcs":6,"id":"rKhqd"},{"name":"pulser","leftArc":"F","numArcs":6,"id":"iZQAx"},{"name":"pulser","leftArc":"F","numArcs":6,"id":"zmhqq"},{"name":"pulser","leftArc":"F","numArcs":6,"id":"8lXII"},{"name":"pulser","leftArc":"AP","numArcs":3,"id":"Si7EK"},{"name":"pulser","leftArc":"AP","numArcs":3,"id":"B4qAV"},{"name":"pulser","leftArc":"F","numArcs":3,"id":"lPDHF"},{"name":"pulser","leftArc":"F","numArcs":3,"id":"ZQOR0"},{"name":"pbl","class":3,"leftArc":"AP","numArcs":3,"id":"6iag6"},{"name":"pbl","class":6,"leftArc":"FP","numArcs":3,"id":"Gszqw"},{"name":"pbl","class":3,"leftArc":"F","numArcs":3,"id":"w2vAR"}],"ordnance":[],"extras":[],"fighters":[],"orientation":"alpha","points":1041,"cpv":1416,"mass":250,"class":"Great Warrior","name":"Voth"},
            {"hull":{"points":30,"rows":4,"stealth":"0","streamlining":"none"},"armour":[[8,0],[4,0],[4,0]],"systems":[{"name":"drive","thrust":4,"advanced":false,"id":"Ln5xn"},{"name":"ftl","advanced":false,"id":"Jt2K3"},{"name":"fireControl","id":"4okKl"},{"name":"fireControl","id":"8GIRP"},{"name":"shroud","id":"bJFdq"},{"name":"hangar","id":"y6T8x","isRack":false,"critRules":false},{"name":"hangar","id":"5zmCJ","isRack":false,"critRules":false},{"name":"hangar","id":"-64pm","isRack":false,"critRules":false},{"name":"hangar","id":"JepJJ","isRack":false,"critRules":false}],"weapons":[{"name":"pulser","leftArc":"F","numArcs":6,"id":"BfgPf"},{"name":"pulser","leftArc":"AP","numArcs":3,"id":"34q0C"},{"name":"pulser","leftArc":"AP","numArcs":3,"id":"ARRHC"},{"name":"pulser","leftArc":"F","numArcs":3,"id":"e0CuO"},{"name":"pulser","leftArc":"F","numArcs":3,"id":"Vf5Pt"},{"name":"pbl","class":2,"leftArc":"FP","numArcs":3,"id":"1PSt_"}],"ordnance":[],"extras":[],"fighters":[{"name":"fighters","type":"standard","id":"Tqq7e","mods":[],"hangar":"y6T8x"},{"name":"fighters","type":"standard","id":"SWoQ4","mods":[],"hangar":"5zmCJ"},{"name":"fighters","type":"standard","id":"RiRCe","mods":[],"hangar":"-64pm"},{"name":"fighters","type":"standard","id":"DnUxR","mods":[],"hangar":"JepJJ"}],"orientation":"alpha","points":641,"cpv":579,"mass":170,"class":"Mothership","name":"Taanis"},
            {"hull":{"points":40,"rows":4,"stealth":"0","streamlining":"none"},"armour":[[12,0],[8,0],[6,0],[4,0]],"systems":[{"name":"drive","thrust":2,"advanced":false,"id":"4Xx71"},{"name":"ftl","advanced":false,"id":"MR7vK"},{"name":"fireControl","id":"pwW5p"},{"name":"fireControl","id":"-KUK2"},{"name":"shroud","id":"E3_6s"},{"name":"hangar","id":"GtPdx","isRack":false,"critRules":false},{"name":"hangar","id":"d_ZbG","isRack":false,"critRules":false},{"name":"hangar","id":"bpB4K","isRack":false,"critRules":false},{"name":"hangar","id":"StrSi","isRack":false,"critRules":false},{"name":"hangar","id":"B54Kj","isRack":false,"critRules":false},{"name":"hangar","id":"iXYqy","isRack":false,"critRules":false},{"name":"hangar","id":"jdZss","isRack":false,"critRules":false},{"name":"hangar","id":"67Zla","isRack":false,"critRules":false}],"weapons":[{"name":"pulser","leftArc":"F","numArcs":6,"id":"6-7S-"},{"name":"pulser","leftArc":"F","numArcs":6,"id":"X6njS"},{"name":"pulser","leftArc":"F","numArcs":6,"id":"jMbAF"},{"name":"pulser","leftArc":"F","numArcs":6,"id":"FKcAv"},{"name":"pulser","leftArc":"AP","numArcs":3,"id":"M38gS"},{"name":"pulser","leftArc":"AP","numArcs":3,"id":"dXeS1"},{"name":"pulser","leftArc":"F","numArcs":3,"id":"xq6TD"},{"name":"pulser","leftArc":"F","numArcs":3,"id":"k8fdE"},{"name":"pbl","class":3,"leftArc":"FP","numArcs":3,"id":"h7JQR"}],"ordnance":[],"extras":[],"fighters":[{"name":"fighters","type":"standard","id":"PhDki","mods":[],"hangar":"GtPdx"},{"name":"fighters","type":"standard","id":"0c_yU","mods":[],"hangar":"d_ZbG"},{"name":"fighters","type":"standard","id":"Ehbvz","mods":[],"hangar":"bpB4K"},{"name":"fighters","type":"standard","id":"ZNasX","mods":[],"hangar":"StrSi"},{"name":"fighters","type":"standard","id":"hYrT9","mods":[],"hangar":"B54Kj"},{"name":"fighters","type":"standard","id":"XG7io","mods":[],"hangar":"iXYqy"},{"name":"fighters","type":"standard","id":"yQKQ1","mods":[],"hangar":"jdZss"},{"name":"fighters","type":"standard","id":"3mXqA","mods":[],"hangar":"67Zla"}],"orientation":"alpha","points":1002,"cpv":925,"mass":250,"class":"Mothership","name":"Draath"}
        ]
    }
]